<?xml version="1.0" ?>
<PyBrain>
	<Network class="pybrain.structure.networks.feedforward.FeedForwardNetwork" name="FeedForwardNetwork-9">
		<name val="'FeedForwardNetwork-9'"/>
		<Modules>
			<LinearLayer class="pybrain.structure.modules.linearlayer.LinearLayer" inmodule="True" name="LinearLayer-5">
				<dim val="43"/>
			</LinearLayer>
			<LinearLayer class="pybrain.structure.modules.linearlayer.LinearLayer" name="LinearLayer-10" outmodule="True">
				<dim val="1"/>
			</LinearLayer>
			<BiasUnit class="pybrain.structure.modules.biasunit.BiasUnit" name="BiasUnit-4"/>
			<SigmoidLayer class="pybrain.structure.modules.sigmoidlayer.SigmoidLayer" name="SigmoidLayer-11">
				<dim val="50"/>
			</SigmoidLayer>
		</Modules>
		<Connections>
			<FullConnection class="pybrain.structure.connections.full.FullConnection" name="FullConnection-6">
				<outmod val="SigmoidLayer-11"/>
				<inmod val="BiasUnit-4"/>
				<Parameters>[0.61773457418070321, -0.54209718683196217, -0.13722946565478814, -0.46490392978066519, -0.81834309704871977, 0.66098287125128907, -0.66461656393908386, -0.38221789755886604, 0.1127513808473494, 0.80426526772545659, -0.33301558672633447, -0.29824559479705232, -0.80554981704822926, -1.0785808114710094, -0.65535385901685039, 0.02692626464571813, -0.51601882218331474, -0.68868671512327706, -0.78839775260979061, 0.88601118656922428, -0.54307287342487909, -0.96186087731732339, -0.53391243716486381, -1.1483987743849045, 0.60295757644543868, 0.4356174431289625, -1.0043584027492281, 0.62818966812913735, -0.63590173253529025, -1.1354584362056905, -0.43977837996411029, -0.6065557085834441, -0.78508454241379444, 0.4090941322803035, 1.1826298676604132, -0.50153345964191309, 0.088316268552578056, -0.73759458977877312, -0.28569089532791775, -0.57172880366114776, -0.88145300310085273, -0.69997335942236205, -0.65337947899655247, -0.14670505946590251, -0.78704848276362716, -0.74289135184265798, 0.38600429350214555, -0.045643139325043589, 0.69438972534842081, -0.94934621618579829]</Parameters>
			</FullConnection>
			<FullConnection class="pybrain.structure.connections.full.FullConnection" name="FullConnection-7">
				<outmod val="SigmoidLayer-11"/>
				<inmod val="LinearLayer-5"/>
				<Parameters>[0.60430910770130442, 0.84605548751282778, -0.97522762313798461, -0.50715924404756862, 0.64995266945068131, 0.26865602662017968, 0.75492674649071012, -0.3672399643772053, 0.073423478931506636, 0.68732102890367708, 0.6820227780047825, 0.62338261930340466, -0.48726256773916432, -0.9321487336936769, 0.45910830373311307, 0.71218537366565948, 0.4175690325300514, -0.5769738413674238, -0.061541115433858568, -0.57693451430821607, 0.4284702684226252, -0.036730679644348778, 0.39690301082210344, -0.62884740017524687, -0.541404271656999, 0.81081679294178466, -0.98629391322026827, -0.89676912752954907, 0.20978810702999806, -0.6556900015309246, 0.10970478296988254, -0.92577367659518428, -0.8356116578034628, -0.41247023017034212, 0.54266005256265459, -0.088317781096241166, -0.33470650538112751, 0.23091201351541091, -0.7859576412346333, -0.76497944052692401, -1.0712186563137409, -0.39754250365677152, -0.26326183363215855, -0.6209840914051642, -0.32067526552228315, -0.10089313311539592, 0.16338089416235144, -0.97566762972606413, -0.55511465385655423, -0.24271673891487999, -0.24659879681074448, 0.74614041123102659, 0.54026830257999103, -0.68437215086069891, 0.43140000205041829, -0.87622672277715419, 0.88582758777775517, 0.85584982951992028, -0.28011724244860958, 0.1227076196766997, 0.50798771864140224, 0.26177779201996826, -0.69657752269264883, 0.65646210166332652, -0.40521718963256081, -0.5774119573738502, -0.22587575390146364, 0.65990529318822022, -0.82459586562378184, 0.4250381091040159, -0.82603293790752153, 0.3645144558353367, -0.70648054621520895, -0.97956194111924133, -0.72011846770644594, 0.26746793140454661, 0.017623409873384208, -1.0738781016966954, -0.98220636082385593, 0.010123613539366458, -0.67603519549711166, 0.055654163805057465, 0.37216457888465498, 0.17490283519946123, -0.53307792302233004, -0.11701841005739055, 0.64682800192174916, 0.079299565519500431, 0.053107007905846257, 0.52833765576843106, -0.31788529509556335, 0.00666415990388073, -0.28922111188842742, -0.21617740867562332, 0.72062424482160403, 0.39561544462328863, 0.45831038479741659, -0.89455865023194392, 0.91886124126814017, 0.5185380410155106, 0.23425390936083854, -0.27716786342869165, -0.5544623015099418, 0.065498391051660734, 0.1624870594718677, 0.66115048571218216, 0.26470583789786933, 0.28482475427175352, -0.17551344278578707, -0.041277374834781201, 0.49329361873988231, 0.35003937936810847, -0.86280210513855304, -0.47955039445939829, -0.49519803102493543, 0.13075235729466633, 0.08656338750376176, -0.90819965625890509, -0.51293672103658872, 0.43569174139163314, 0.019829737187263545, 0.098350304258852328, -0.010000676457595233, -0.26162501340457162, -0.8842141436830705, 0.057988750313537687, 0.041436165376766192, -0.065679592397804756, -0.17506552243823251, -0.335422745649882, 0.77470228505600702, -0.58351956480815659, -0.99797162025001573, -0.31075964920441923, -0.53137104730190865, 0.16084848254683398, -1.0443478387821017, 0.49965673773229546, -0.80993470807282175, -1.0398525728560624, -0.68753528806714892, 0.39999038018913413, 0.50817667856052062, 0.0044624723092086798, -0.26099184411978066, -0.70685076533748514, 0.58466539134718343, 0.30275764192910448, -1.0055611970705183, 0.013782004888814755, 0.31890811436725192, -0.1638734656345685, 0.68525152516592658, 0.64868772375748351, 0.71835652429038022, -0.59257825175894574, 0.59249104085789417, -0.60462795104451161, 0.68553691891254442, -0.7073209507824173, -0.28443811729624968, 0.41979849573700129, -0.35412461370253046, -1.1635614411917294, -0.90843849408721888, -0.15611141682576568, 0.62619146889043842, -0.74248287338350127, 0.26843359432375785, -0.49706658020256228, -0.53801662264583783, -1.1546357246780277, 0.83914071234261067, -0.13906063057537504, 0.18032192024162408, -0.35717913022765008, -0.46814387936640789, -0.43999002982013707, -0.11170777003211525, -0.19539788288038476, -0.80512379670961254, -0.49669765365430957, -0.652056424522377, -0.95854633206124895, -0.062998800546652398, -0.76952666222260369, -0.57416580769959413, -0.41481023033695424, 0.64255739728833827, 0.28572354222723267, 0.47716826266148932, 0.65548966176047874, -0.3375405563498457, -0.39574559425544747, -0.096337007261660224, 0.4714065511454506, 0.30744729564026535, -0.42315762689291259, 0.3166974359336906, -0.0018776394920357797, -0.65742004308814095, -0.79281604586764398, -0.64963221910702729, -0.61731223910584487, 0.21325355775436855, -0.61829038263408431, 0.63948311829248672, 0.023832311485142504, 0.53817457833581361, -0.017779380250618825, -0.52346367595543286, -0.2590086445876395, -0.53834489172116695, -0.92560274217639971, -0.13420800062382685, 0.77588623774820509, 0.73060539484537457, 0.042070621003961431, 0.86719370881455071, -0.80926104256514575, 0.60274690071155823, 0.16232521140694087, -0.89966833979991667, -0.42396467518055692, 0.3329289841548187, 0.84779025850508283, -0.68994086843352398, -0.48079960550095274, 0.37928240999852714, -0.71161089427346724, 0.058258664246544183, 0.082953701679377032, -0.40618446479754972, -1.0133581421881364, 0.39452556059818283, 0.25406877929548749, 0.009973239837775422, -0.645037413781271, 0.40060061862040153, -0.53819011225387103, -1.058380132822726, -0.48073549425809481, 0.17014672234362835, -0.7509800986491485, 0.44141275440996758, -0.55940357838226284, 0.23963073434586352, -0.78509879105780667, -0.10888288600938133, 0.32367951069330747, -0.52632478453834286, -1.0838913737105844, -0.503005059914158, 0.09694823367350229, 0.094403370824547084, 0.080362061415259242, -0.54558723185833902, -0.87989978992297035, 0.81306383263791659, -0.41536566266113151, -0.027586009973519957, 0.0044632210566079456, 0.92056645195812781, -0.23762971258337695, -0.93028917918671028, -0.2475079599760806, 0.48216260826597984, 0.57362413273986168, 0.28840307492821127, -0.38053777537957911, 0.30396447827125989, -0.926660333308988, 0.54554145260925335, -0.057558254255266943, 0.85092639623949085, 0.47156545840200342, -0.82216704664515272, 0.41142037265141179, 0.97314751816967837, -0.31936389450099267, -1.079471932909787, -0.87011582027509049, 0.52722845802574592, -0.48036914549053172, -0.31926338091825113, -0.95564772634976292, 0.48018441779547355, -0.43671061766539959, 0.29524447431906337, 0.59852369900651448, 0.022081493618360971, 0.52997003657361486, -0.23700576473163035, -0.092435445709595568, 0.64942767804625301, -1.1430771913933855, -0.22429045256268057, -1.1930446923102902, -0.70738741286509099, -0.7501291676780425, -0.93161863503796527, -0.82091857003054369, 0.21243817678774604, 0.3687539770644413, 0.94135007111781721, -0.87158146824371086, -0.54089401979498763, 0.087641236060463382, -0.95403531508735473, 0.04450783583238388, 0.028429629969541289, -0.25273447645582947, -0.55511148146380329, -0.42407414353415185, -0.016671243122230651, 0.31943809440012255, -0.38605932583858565, -0.37724841957643268, 0.57217149157130842, 0.99958225963576286, -0.70567786483039463, 0.57984544335037458, -1.0543222391272187, -0.45377950325876143, 0.1228102874223391, -0.5454826014737143, -0.28434707823413941, -0.13135358820495896, -0.6171596183633965, -0.1709721887869354, -0.62713235035804804, -0.53485810361786812, 0.12792246305375318, -0.87646160821745889, -0.19133007652280859, 0.59169268082155269, -0.97572608649003678, -0.12269022804169509, -0.59811934094140062, 0.16296762213723529, 0.42217155917374244, -0.28689635824341897, 0.36493119823433107, -0.60823025826187049, 0.64145428186830078, 0.5042101248050127, -0.3082445831913771, -0.75210148405643784, 0.85713420147646557, 0.020305817535186389, -0.94152184434268316, -0.49860961371746143, 0.38224890374297632, -0.20423301659538373, -0.031873444007055038, -0.5624460312339209, -0.28205969154040395, 0.69146529964267656, 0.21976875629531248, 0.28935091609808283, 0.34345457368038701, -0.15678308335891758, 0.68002867883898532, -0.8342498332526469, -0.81207561059068978, 0.42594773413256865, 0.52627890701419799, 0.6290554592734211, -0.37755576188247597, -0.93655509622653854, -1.1116385668378534, -0.38764381370345435, 0.53040209202723843, -1.0176272138900155, -0.50780356833833795, -1.009498386221013, -0.0026843530953172606, 0.25543891877507668, 0.13847934631287295, -0.76980929083860894, -0.24100893593059405, -0.67281977514387581, -0.33367879842207882, -0.96533448760294471, 0.043462635886276635, -0.45328716457547202, 0.19644442911322191, 0.052482172011196274, -0.25639959369034399, 0.70819624453106245, -0.67214535138800025, -0.96709821911063709, -0.73123733966487126, -0.95253352625440213, -0.72215057977354757, -0.63042933309977944, -0.87929472879638793, -0.10284564693219142, 0.1871329255308618, -0.54948667570896603, 0.4297924830056255, -0.32355177938728458, -0.29540956140262287, -0.85595043325843456, 0.4119674829918985, 0.17444500175946318, -0.50550642223041919, -0.060117904258022929, -0.46658484176337311, -0.61643387167270625, 0.14108401514896607, -0.13865037278801245, 0.070481301564772988, 0.39250449660036973, -0.46157226280014235, -0.73825556251067082, 0.21448963530212831, -0.15735078941728645, -0.19547532093144657, -0.61970873243613012, 0.70583528908939219, -0.63209148823100958, -0.9544803672485791, 0.4369814175317745, -0.25231192843487948, 0.071230643550532977, -0.64643797568994454, -0.95563132066056278, 0.03995373397055059, -0.54840693887776037, -0.75958637203566404, 0.6366097944487551, 0.67566107069301173, -0.073691043416233129, -0.22763334913781871, 0.75826237079962933, -0.42034392790456837, -0.35430989339775487, -0.1493828168178854, 0.51180875495240696, -0.16143448346213321, 0.58807030236115865, -0.55253194011031992, -0.95906737524028218, -0.88696519048767086, -0.24420808757943405, -0.73138484503022105, -0.67291658283796663, -0.80705927577153713, -0.75095488236327512, 0.83837534369008371, -0.68802394087517016, -0.57615329727436793, -0.32026224349242732, 0.62390296567839676, -0.8534818526737612, -0.88891844525247266, -1.027989314554651, -0.98552260718387674, 0.72073439162637154, 0.084437723772860684, -0.29391663778806004, -0.95701584332706846, 0.32369456660108553, -0.017046347276052452, 0.10303741266168805, -0.44515595423893595, -1.1477960315409488, 0.46231129182303476, 0.33406651255937497, -0.13242589996351853, -0.49051754246448137, -0.28144461345557592, -0.21501677009232373, 0.1938937325821381, -0.3625417693123435, -0.16367894739493821, 0.22657443068942382, 0.2729427664349906, -0.59353366435590826, 0.22741657247534089, -0.78396612408476696, -0.8772779363616191, -0.10696263554926688, -0.35327193607417634, -0.45851514860898668, -0.66572055967582111, -0.86570547562140543, 0.098609321624225824, -0.84654574489471046, -0.59217655018865989, -0.8749783024266341, -0.71361191276922076, -0.81850199566392368, -0.14051127000913965, -0.96989986992077981, -0.47066954164428687, -0.017319539871641483, -0.29279696077719131, -0.67888470866966377, 0.26221913119456791, 0.28254968673237357, -0.13114619350555953, 0.16598669898998894, -0.25533369746470946, -0.13359940930564318, -0.22753463757381512, -0.055804076728598932, -0.34732177720474272, -0.3391721576050214, 0.44877667186873493, 0.031004156672869695, 0.50831633307396784, -0.34849044465144302, -0.36769276691200481, -0.10683565791446507, -0.8031617427151363, 0.35485564381311269, 0.11740944096962333, -0.11202578362290248, -0.44060312835860227, -0.72654907704327709, -1.0518990680390823, -0.96499794048792753, 0.71019156204052047, 0.54029113926780681, 0.56679622291327025, -0.086416599349680837, -1.0917906946703764, -0.04825949568683794, -0.95732525227464371, 0.013908134071160889, 0.39828000321555856, -0.69046567800070235, -0.076345858925969776, 0.60057276773752533, -0.40376831670925911, -0.19705165695243929, -0.27809033836468594, -0.89405357401497143, 0.14251704845721233, -0.097293678704893805, 0.59416146120395974, 0.65924720727374231, 0.51070138813892529, -0.36624123491945026, -0.88161392702064934, -0.25886969991960618, -0.38286384565175763, -0.30923174163135397, -0.27822629529574289, 0.15767145795668391, -0.95802049432220582, -0.36989582721589465, -0.031977461510335287, 0.11721374949314084, -0.39565314091735809, 0.16343156321381244, -0.17802215090876772, -0.82135926142185722, 0.90756844155000749, -0.53138538363741972, -0.35851759763515401, 0.79500905889056006, 0.09772990396855856, -0.40739586356286223, -0.15705661614219549, -0.88400819225317306, 0.10696198874868483, -0.36894265412231542, -0.12420810335522536, -0.6408767723172254, -0.58594372890374224, -0.51568802144288317, -0.094767587148833529, -0.96099092328804758, 0.15440244426416513, -0.045903966276151793, -0.95628209738320591, -1.0272353882526868, 0.59357927017081868, -0.21276970146181265, -0.12108970100799751, -0.97211638667922551, 0.37899796849128375, -0.041200156482449596, 0.81234487340347772, 0.56308516262239383, -0.51746842798018255, 0.41995971246648528, -0.50058832215552374, 0.2063520448233431, 0.25917794067249239, -0.20142278819563231, 0.41161208502811208, -0.63043034840772061, -0.33961527279810005, -0.60772626083299874, -0.63096052618297771, 0.31367069592509378, -0.12430363138442645, -0.96047133432477949, -0.32496296100664701, -1.0066928284883494, 0.61216728340144499, -0.81972444082251572, 0.53670741466904237, 0.19066309030404324, -0.41270215605861005, -0.0092500451346955483, 0.34967165696211849, -0.61738084101041479, 0.23082026045220361, -1.0620869832521544, -0.057591757507754852, 0.1977534577155354, 0.059392907881828473, 0.056203935343745438, -0.54704123145198058, -0.47076566022666178, -0.47940396470234764, 0.26715584954916943, 0.095775575430649074, 1.0064763476791618, -0.31231076821136827, -1.0189480598606744, -0.70785938902164669, -0.67881272428817641, -0.49834449453921059, 0.60055400690187333, -0.13105875963403671, -0.5319711861167169, -0.14257449486737098, -0.22880901330052786, -0.089898950958494178, -0.42786119377739923, 0.32036726109118435, -0.080035109811043462, 0.16099398675862853, -0.40599339785876182, 0.27478413075713265, -0.58165635330170273, -0.051008631970870827, -0.11994006400554834, -0.071942717886257751, 0.68861614303364682, -0.27136674012581069, -0.78739033799769176, -0.35434408862028038, 0.95714551996188513, -0.39008556562329705, 0.69425073638902013, -0.58016706748548319, -0.33284343778751008, 0.71692399087049063, -0.65124011414598915, -0.25604622549681033, -0.1810646923929935, -0.41300174893018576, 0.50198395006099683, -0.064643913905438624, -0.49129880515335866, 0.82538329393318854, 0.16794566940649774, 0.7205828096279111, -0.021567549493662439, -0.52563707484471811, -0.47298921606571198, -0.17027763497050796, 0.62482291892866293, -0.81965357208778078, -0.23322582305923897, -1.0556113744558961, -0.36657667807138594, -0.21072291956241326, 0.69094123768264548, -0.90831196109591483, 0.67527347394946469, -0.94831690851806139, -0.21706086410643363, -0.22278330347913514, 0.38257060509245916, -0.88119022988354223, -1.0105703582354415, -0.88162055943200257, -0.36544999984816667, 0.6153429585820015, -0.036926757826248928, 0.18778267130112547, 0.91033546835734147, 0.47597031315510058, -0.75586934210476919, -0.39428852013416055, -0.62537732647236999, 0.57038765814783943, 0.93065991892149758, -0.80969742109030529, -0.13832575221419999, -0.67551298744500488, -0.25668441020540755, 0.28585854081144801, 0.47411600194912507, -0.88874310837616111, -0.65152416887458808, -0.73330277828006718, 0.06364015565158393, -0.7056916354758942, 0.1397064704071099, -0.57022900375462404, -0.16654430995976868, 0.12710017397335815, -0.56900886618855817, 0.25415740057976949, -0.42179645401849325, -0.033867923433220239, -0.89411341894062002, 0.14501024681550187, -0.05021186370897579, -0.86715102933631771, -0.26391666576825928, 0.091998120904902933, -0.46771755597162817, -0.31170682374358016, -0.74855909290024747, -0.46611469557678747, -0.43351137725404765, 0.09961202584347234, -0.68456865935724542, -0.47801310757961302, -1.0590584708349557, -0.59016313339512561, 0.50115205668044682, -0.38429635606425011, -0.58664023299770729, 0.77875400648891613, -0.28983244639231637, -0.21980540128773057, -0.96301629719548421, 0.71714828325772895, 0.38277948261385547, -0.074391446165732414, -0.071301096565020414, -0.55757357339636637, -0.96616585941359423, -0.55559727784317736, 0.31402620824841426, 0.65377824083120828, 0.75723880037323499, -0.037751655848256717, 0.47983295680453608, -0.11204886212709048, -0.43518860162965389, 0.44356983289465546, -0.3063010246042252, 0.23615056775738641, -0.69524603330123735, -0.91733578214952038, 0.36790444185625926, 0.53535668642829659, -1.0068687915748056, -1.1572437398161746, -1.1382075064484538, -0.63971487419739048, 0.64313700819375419, 0.27767132442920928, 0.15598178049723196, 0.046696968730363698, -0.62093164727596839, -0.70296034760055726, -0.27397724694904707, -0.99068432693330033, -0.7419008021772221, 0.19094607060237792, -1.1017514809115028, 0.67440703328842977, -0.2741766703849432, 0.3301245439048433, 0.30476159730546382, -0.90528174746545131, 0.64503863615274182, 0.78803190575045978, -0.32113220775848755, -0.6605847027512185, 0.71754974000006866, -0.83734740458398826, -0.38301561482956492, -1.0299671730769802, -0.25748399770780711, 0.70666314915533168, 0.72933481069511796, 0.25037883192452132, 0.41993849491826579, 0.34582126013179931, -0.83608597507247995, -0.32438221052813682, -0.56859205723624684, 0.063579961840701374, -0.16169079104843204, 0.2951759589775928, -0.2278308057849224, -0.72683619580181558, 0.53185560684400879, 0.45892119945737991, 0.19024452241143963, -0.81591993833875787, -0.39559393885290578, -0.37471871835639697, -0.087172848393211294, -0.26720174215250153, -0.75555198032143811, 0.30321998637398762, 0.51950104414402576, -0.63132916479055001, -0.40936197902559107, -0.17532359113180729, -0.91282160652149025, -0.49831970383613738, 0.84134460939596412, 0.39121789699425213, -0.12068993805280354, 0.690628702023934, -0.42311401407386612, 0.55231923629495261, -0.53769045712736729, 0.10110179040905837, -0.51956673845056356, 0.56316822358634155, 0.39309376230613968, -1.1546159764948658, 0.71045835319952189, -0.76025796462182982, 0.014057193990890652, 0.62195374205213616, -0.43153200761241983, -0.12723601944930485, -0.88225923019395269, -0.022838405379847972, -0.26035370770727478, 0.34547764146465154, 0.17677783364155247, -1.2757172003524544, -0.68206447813690407, -0.1929877077273969, -0.26435615898742237, 0.60451922321171903, -0.62496982895129749, 0.042963058066604838, 0.026228977905890721, 0.45860605017153977, -0.78233712047886905, -0.10922365066089056, -1.036984251845539, -0.13058801616014426, -0.30984878586341807, -0.32751393244552679, 0.4488459235018985, 0.092672801282707329, -0.18510722824438325, 0.25109671562849084, -0.24146194698369822, 0.24294424384629937, 0.48002314079960778, 0.20209935653744809, -0.24357444142473555, -0.23254987265293195, 0.083408443982165806, 0.59071916300196525, 0.8584326292117479, -0.19514255744621012, -0.79972091826047786, -0.64812292836284824, 0.5794773975268962, 0.066707864224511207, -0.85748452664904773, -0.3444181769917371, 0.58713042734625032, 0.66395306628136519, -0.061300583842892213, 0.5983996400961672, 0.14310556155975868, 0.11676383418396524, -0.64785369863827602, -0.78119711879560327, 0.71260242282838759, 0.59548585368147344, -0.92023264396917825, -0.45305062570838245, -1.1408285764497332, -0.78527458353708501, 0.30802851130756054, 0.33950729009991748, 0.0070906922263336766, 0.27071810989402656, -0.41611837085926534, -1.0540555815763137, -0.86076622077684317, -0.92559775275909351, 0.63279232370316785, 0.60734460855319139, 0.12797357520965127, -0.3279836052973204, -0.8354576265534257, -0.60381356675703068, 0.094408272928964809, 0.059068620145893681, 0.069829667989970992, 0.67315076332498558, 0.035528401869750793, 1.0676557417437127, -0.28586250189916451, -0.0013052245630999955, -0.53897521306946827, 0.77473282981823688, 0.058751930766732657, 0.10293331741776501, -0.722206006155654, 0.74493310171350546, -0.32771689895687051, 0.095059176229203055, -0.042104161761947312, -0.11382459824374733, 0.47239983719350537, -0.38296100478983613, -1.0697353182219211, 0.3627009590737777, 0.34593912461751247, 0.13777660886855023, 0.49874896643929473, -0.27741517596917675, 0.50614981788639468, 0.59065981467857587, 0.27148027730569024, -0.032080759399737799, -0.23228872947355492, -0.26881479193473856, -0.091276270279872299, 0.14098224197027834, -0.51012413746811891, -1.01061949980585, 0.070118799664970491, 0.14882049228852928, -1.0044660079538057, 0.29594459834879866, -0.87794887543573463, -0.76302601824736982, -0.14397053513973584, 0.10567130833770562, -0.019912316934068287, -0.37432931289553284, -0.82407849277907963, 0.22214091742890835, 0.50026515649496073, 0.77032015321716285, -0.79669469648466407, 0.69431597444695714, -0.80431228025877832, 0.59445467281654141, 0.69141071330550141, -0.84283405030590042, -0.93314331036899889, -0.3446828673502067, -0.014096623580331147, 0.43502225909571107, 0.63627724901668448, -0.167632580737863, -0.27686492217909614, 0.72737832940454139, -0.89636428073050989, 0.68360843529070936, -0.56261563419082972, -0.61868379690715314, -0.74180861275066656, -0.27979912353434427, 0.24457669563081791, -0.98606971053335479, 0.048147527453078987, -0.31663581998141438, -0.28033208930692688, 0.075135502854921599, -0.96544722221679946, -0.53493852789755281, 0.18653548823243118, -0.26317239665223813, -0.099517048410080647, -1.0477974803286967, 0.03829615680748729, -0.27539333259414378, -0.87150979240950677, 0.2809151714813381, 0.65622904695585982, -0.91395216617554531, -0.15429520455969153, 0.16182468171392994, -0.24097463678136866, -0.89184258953707962, 0.36661807091588189, 0.10596007361360103, -0.87787103518985476, -0.96379175156874852, -0.10171179738012638, 0.69850443556798536, -0.67452138466495204, 0.73437172863042677, 0.65914236379398938, 0.72188151351219965, -0.88805752634040203, 0.50319014532706108, -0.75063293012693622, -1.0037147330046041, -0.61503464811430775, 0.62293267349850034, 0.40819766943395219, 0.52934057481365493, -0.36010493004655575, -0.38030062822802235, 0.44530031879572002, -0.075707449399889409, -0.15932685757774059, -1.0390662894907474, 0.036014511233697248, -0.82837746272011981, -0.041524220581634123, -0.48461520327128738, -0.17354717360254887, -0.33086737069997002, 0.23330097287769822, 0.44598886975490604, -1.0940504973465155, -0.054007078917558113, -0.026235577052587198, 0.047872417801263577, -1.1018965252538733, -0.42630941162597213, 0.97159199413169128, 0.82907035524776684, -0.68557368671139896, -0.017781927001592493, 0.097301692099088136, 0.27663839554549979, -0.22168249538611234, -0.9881350147063257, 0.67956999604022061, 0.77282561307306086, -0.62167383491607675, -0.66201755416014163, 0.010116569058655244, -0.3145209921885247, -0.38715791233401803, 0.4556753788240791, -0.90386309904768747, 0.55491826850040737, -0.15854940857600738, -0.45562358055284757, -0.060435450054466731, 0.35014329107928827, 0.63736535593142474, -0.49079178502577875, -0.1506051333564572, -0.19947514541937836, 0.035192471656608403, -0.88651203952472191, -1.0185330570995634, 0.37982389224211105, 0.46975485467622641, 0.59149934602172194, -0.4658460079481353, -1.1343918293090067, -0.49479921670025928, -0.15190620774890656, -0.52688447025813501, 0.53738282176301277, -0.6300114546186939, -0.68120993692566956, -1.1325127073710084, -0.72674854141154588, -0.9287409578653576, -0.070983697765343926, -1.1795138351616694, 0.091770610103729999, 0.42802064893464575, -0.25244914878946617, 0.50178121075257121, -0.66422389442910279, -0.072155884827016514, -0.22081838970039511, -0.65599308620187557, 0.13840041176718595, -0.091847063764217945, 0.019506148906297559, 0.49439627267532604, -1.3598836748377274, -0.076996926389241785, 0.55122207196271766, -0.63770846030746775, 0.25562489307623942, 0.099688502910987964, 0.11628135463156258, -0.57626433560232337, -0.25806074578762239, -0.63432341782455992, -0.89453452166732461, -0.86076833102372097, 0.6143147835676549, -0.84031095806111311, -0.0097619401259653148, 0.082898183952096013, 0.30056796951766873, -0.80402919178468535, -0.48670518813574359, -0.23940211133338546, -0.73951395129158826, -0.14599727301519422, 0.23288260326527904, 0.55828593696277751, -0.40252049294370584, 0.23815659043008289, -0.076317137597958759, -0.077203528959971374, 0.031079160505843476, -0.72801547373406428, -0.51648491237280914, 0.89722885649440798, -0.41850757851768217, -0.52663002034934847, -0.86676601215433968, -0.29560237835657022, -0.1506413565683471, -0.76713320816251418, 0.90221928340442858, 0.41373279747697222, 0.92599405602727125, 0.37793385453513878, -0.626172718146211, 0.33694825589248117, 0.88924300110876187, -0.66594241509325602, 0.50512832607903146, -0.80420590276772019, -0.96560235750545365, 0.54478011543158877, -0.54476250013943761, -0.74881445977933847, -1.0136462269163373, -0.28907824338323329, 0.15024108207954007, -0.027988078181192755, -0.67769247116599374, -0.37016781825338929, -0.16444923257985986, -0.12934381648317966, -0.7514409480911235, -0.75647532333613676, 0.27889801998041452, -0.1216389344520649, 0.46320444955911777, 0.45719862400689043, -0.4239224334534667, -0.9361730409885719, 0.6948052880437452, 0.052689228938090818, -0.60195997176812055, 0.64164683874824957, 0.58633875936209456, 0.3932916691730543, -0.64978141527744859, 0.8871056267049573, 0.43778776762515514, -0.64537332127231606, 0.3532562461528494, -0.51619305808949012, 0.30618667209964201, 0.85111645693271309, -0.10665276525378446, -0.8889038066187005, -0.75533006619367393, 0.37743095990327213, -0.63028808762699851, -1.0266619220844568, -0.7511087776516846, -0.41325183957034195, 0.18848472874895644, -0.19891837043773905, -0.57429676460587875, 0.74809399721249537, -0.64698741664535731, 0.60663175415098691, -0.37785879160463587, -0.39575255518313734, 0.66330583899332896, -1.1733989265991676, -0.91748947474727927, -0.1909978636237098, -1.03164046555439, -0.18420626502897994, 0.13067931833449054, 0.66959863368381278, 0.14858325464544186, -0.035586397780330001, -0.81429037741400612, 0.14920457073326931, -0.8231877939125799, -0.0060786012281958193, -0.0049071800201129136, -0.96822363172779646, 0.40679094759838552, -0.43824013431865755, 0.34986265673020789, -0.22985730263553097, -0.92894372465466224, -0.01546034202658131, 0.91781644386391248, -0.90931208621915527, -0.43846078628525359, 0.24429941111509457, 0.63163389364831868, -0.25033898183089703, 0.084682328562044856, -0.87609997955148111, 0.19878453405394636, 0.69245626804027449, 0.60690950745136452, -0.6267930472056682, 0.14558504298444425, 0.48210915559635953, -0.62699105321223991, -0.52042153777479583, 0.26138953249350383, 0.33273027772741248, -0.017648071779449583, 0.75540545679902349, -0.08766525766584489, -0.38934637571710706, 0.37588854634025437, -0.48633027013789787, 0.0015738115972928762, -0.21500303626139555, -0.86857562950464806, 0.42482259538296424, -0.81545031374955457, -0.8264659305345684, -0.3349691761431367, -0.31845350961439378, -0.4677369401481461, -0.52107461291939527, -0.41778731032313199, -0.9271413809557022, -0.6727987646026008, -0.97149153315880399, -0.0021381636819272146, -0.17601159651750489, 0.57452529674082142, -0.82555093806409308, 0.60352308079879502, -0.1412321283637106, -0.35766840927785032, 0.6654783642024148, 0.57349133309044098, 0.94420098584743495, -0.75001472654823254, 0.33845636507791782, -0.40455440915325469, 0.754951272592569, 0.38980146597685517, 0.2377480244402852, -0.81331322004753748, 0.7402010912808048, 0.76521090689129301, -0.94042268111776095, 0.45406317381889477, -0.80784167698639187, -0.29932619172148656, -1.0971452228014968, -0.071342566106205457, 0.32445610080117965, -0.105906006194513, 0.40285002096846723, -1.1305358650415798, -0.11365817879311527, -0.84578015022817399, -0.29150865525508862, 0.37663601842855288, 0.42625239914039253, 0.52470018389099315, 0.44054678113880813, -0.10723875900161386, 0.56668591825004544, -1.1312965837724138, -0.88303397948010787, -1.0675477893520133, -1.1840934506189551, -0.63476515356654328, -0.71760900664468541, -0.66812834849403691, -0.50392820405893779, -0.73511792152240163, -0.65039074614345271, 0.33767838720463172, -0.2732001613878276, -0.82033968872454655, 0.85866590677360866, -0.78030415234271111, 0.41569968053273065, -0.53389734964476276, -0.015239651534714379, 0.35034278392040707, 0.50272227291317462, 0.17302006099909126, -0.73240812217269691, -0.47106818119045119, -0.75084640137867098, -0.99130231739515429, -0.40227642239641026, -0.084407960284286571, -0.47285877051896114, -0.43155603620417476, -0.086962195274217891, 0.58151105024083871, -0.68996631878670855, -1.0588721920334263, 0.023960017905836677, -0.270485016420901, 0.55939222260313637, 0.17257267329897508, 0.45655026296263407, 0.49294067472580561, -0.78558713164298244, -0.75565819966739145, -0.59370346816705766, -0.75274277159799774, 0.19031856910131342, 0.45392300045206085, 0.51879662012563943, -0.93749057614184494, -0.07693325480784774, -0.97894052569184997, -0.02103600286231035, -0.59144491321702786, -0.91853303469061898, 0.61709529400770236, 0.070162434343820398, 0.61637756377790198, 0.67098069878076894, -0.85272006614808216, -0.25107819642398937, 0.52797287103573121, -0.45194748318954547, -0.37135909770545811, 0.29865765894589397, -0.16707588015942829, -0.94556743023706624, -0.24801254402133432, 0.83652205729915086, 0.74429628624844835, 0.80644408713870608, -0.88608090015486185, 0.43353079017828106, -0.55263282839986383, 0.67813082631737265, -0.72798043149957659, 0.022668343722908654, -0.1727272130239228, 0.17524665139842446, 0.050096546605492474, -0.73529566821744152, 0.31872801042137711, -0.92937909436321609, -0.50067000933699501, -1.0106268594500369, 0.021218615747676133, -0.039739046553618651, -1.0718026699145995, 0.4145680313284596, -0.86500461377688931, -0.93812270480414461, 0.21959144019872737, -0.20079243703251839, 0.89166502608194609, 0.72225437303187401, -0.61199414221762705, 0.081475240167528301, -0.98268830271684215, -0.008947101722139925, 0.23646700452187333, 0.77906259790334897, -0.58814949832559482, -0.61977820755213109, 0.25753799240398406, -0.17282499340062576, -0.86670106630644839, -0.99293351421335163, 0.49320284355974603, 0.30305711695335202, 0.88417052645630823, -0.85892489232357661, 0.479901896822723, 0.58961715862173858, -1.0123736744770195, -0.91027505924127294, 0.62942062044077218, 0.59009043796757832, 0.3851767668078202, 0.11191080701223168, 0.40158149953256406, -0.17604678898486717, 0.56806872818975007, -0.68192745196075033, 0.24508537897518887, -1.1550795739652853, 0.049101591633786509, -0.6776665220760868, 0.45958766551690261, -1.1542054387964575, -1.2165933363531911, -0.54818636665619225, -0.026678478112759772, 0.0053865913700278266, 0.54845916750495582, -0.79923676783437669, -0.83420180837327595, 0.069657540242772251, -0.30206751046875369, 0.23251534264617613, 0.19790578092704325, -0.70401838220573909, -0.018105666677271259, -0.99532005780788213, -0.076646623007748299, 0.41975966987195701, 0.024622135718681947, -0.49515037627627639, -0.031433550279571454, -0.96909248064771347, 0.71188016618197425, 0.40864045001930399, 0.38598572107260326, -0.64763258544423097, -0.52657615790842782, -0.81851986853910785, -1.0215245942933557, 0.32859443506091462, 0.28188887357885745, 0.78958496176766357, -0.15657232208394917, -0.88797269557941805, -0.025860318444158838, -0.35034085397798204, -0.68084368942189055, 0.33828898692850901, -1.1353266850740804, -0.6587127511378813, -0.7531721056051971, 0.585429715857129, -0.33398676262501054, -0.36621775110326416, -0.12136235363211061, -1.1306103469839677, 0.29068988573432436, 0.061968862897334449, 0.42077107770858702, -0.89599151881163919, -0.84486124110877281, -0.31016314605121542, -0.87791142208870898, -0.92614563499465064, 0.50856117964677749, -0.80541905534027158, -0.64832834656990113, -0.65443861705198858, 0.93985434472394513, -0.38349411318667581, 0.83364003548223542, -0.33119795432478522, -0.31100240621652298, -0.80885728309493565, -0.30188776223192365, 0.24184843922009561, 0.35310607354982215, 0.82535339110509065, 0.69861120193509774, -0.035938612642356461, -0.37288313933546186, 0.85787968863939668, 0.14881948716966423, 0.20211805924464024, 0.50777723892995408, 0.87126688998000679, 0.27408911917156847, 0.94300048041777507, -0.43140335692351034, -0.79470353130711469, 0.12572787327932411, 0.94503913534917827, 0.26773364304319924, -0.095204383830671424, -0.45032897055257948, -0.04027219577065648, 1.0555854952048049, 0.54033968680341904, 1.0354241125831058, 0.92572956013452601, -0.11865558951927233, 0.74614134720034453, 0.96344357851352536, 1.0349408913914007, 1.053372153979607, -0.078602357558637759, 0.20056549260512538, 0.18095060250205597, -0.52625585055629309, -0.13968861698479265, 0.67511574969458366, -0.74594264934045595, 0.22663248828988916, 0.30240704193327905, 0.70332705767654136, -0.90516636354766045, 0.32052634620498816, 0.72381923400893211, -0.41665599459275648, 0.034955495095072807, -0.30547369065287744, 0.057636957872680569, -0.39280582949800252, -0.5525470269298578, 0.41718824486994555, -0.21918267486669063, -0.66126617438527757, -0.57777182720989195, -0.74887260306363723, 0.57933687298224101, 0.2022610757385607, -0.29235558104319076, 0.11757981770284397, -0.52244984288123608, 0.1700143724971295, -0.62719121737971661, -0.43593621533151289, 0.19669238428970284, 0.03205096221851185, -0.44612413864056139, -0.93582015430128052, -0.94275929851117746, 0.16729781807939187, 0.2092307303193221, -0.10667060319069925, -0.49246344909242351, 0.092575726760577251, -0.13103400703280596, 0.994014819321415, 0.54026204270262479, -0.98643829165017272, -0.2582571618357784, 0.22031973242804714, -0.9241370851611711, 0.28990417056167489, -0.80726833966121547, -0.88639292275738646, -0.58208021117090603, 0.41269311942728515, -0.27533602508998511, -0.86288663444839386, 0.66839112997486505, -0.73932456327942986, -0.49262455072598466, -0.52092219139805063, -0.82992840931611034, -0.90309692420279342, -0.052147324320442938, 0.15349200772050439, -0.31225806965073782, 0.41683659412397728, 0.84265092369123451, 0.51868558131698927, 0.48187727987623064, 0.5150777684138198, -0.2046860231503087, -0.61570446413410695, 0.60512744886989522, -0.6002466293232559, -1.1024320331061952, 0.13485708768016169, -0.82804314802574541, -0.6171947274435251, -0.82583400789788586, -0.88546298377017607, -0.099746070568810755, 0.46712269515140054, 0.40189554472079214, -0.14517773063080233, -0.12118884106563749, -0.75932619508431221, -0.23085869620597554, -0.88791009287926759, -0.25062870566182588, 0.99212489738504306, 0.057166364353789523, -0.30088182514712025, 0.37749750589111364, 0.15634708079412205, 0.63301603418423968, -0.45678734116709185, -0.078742824534063963, 0.37173017891779286, -0.90790961453412211, -0.078284053970265624, -0.58616932839292357, -0.32695617991844028, -0.79991537514703337, 0.68416779368682756, -0.66852892705120082, 0.25512280005365767, -0.98446072619226943, -1.0554203952055368, -0.132598771177563, -0.66356241764563595, -0.15551247844388408, 0.32944665715543431, 0.12348502108292775, -0.56168830765052624, 0.11271765264606755, 0.40665990030689392, 0.37782430782617749, -1.1702454550174177, -0.79134784110687306, 0.50788382993111203, -0.083793021363542122, -0.099684368302401058, -0.11241690812225714, -0.27455793947066054, -0.88438456759604323, -0.18996116570691476, -0.090105961536504964, 0.062962981921462838, -0.08284063555311004, -0.063307947230698325, -0.98876600249925817, 0.66063021707080449, 0.14522334002631976, -0.68569292593988262, 0.49774517948468883, 0.78390789350056977, -0.68286019963282973, 0.062681509210674585, -0.32281296564529582, 0.45697233567894785, -0.094880033517920501, -0.79452604346026323, 0.24870076561236598, -0.92340572796403808, 0.21539216173597761, 0.16247679388537145, -0.21520747769309564, 0.60048601576722338, -0.55436609575678009, -0.88099526445398224, 0.10337390433004662, -0.29396302392393886, -0.96332626903134377, -0.98471694695305889, 0.5008402957939837, -0.7905220513590856, -0.95307864946950382, -0.063548034152143718, 0.0029124465426225918, -0.31051546662995733, 0.0036289491287992658, -0.24549615528429039, -0.87949526665569011, -0.0060513901349125467, 0.49319904514574903, -0.87258800248453361, -0.71474241323825638, 0.15909605610565852, -0.2751618102303352, 0.27526248012573784, -0.47590965325407764, -0.073942358841780423, 0.63663949822209853, -0.25159646885343384, 0.24109853661600675, -0.40350363204771428, -0.54350326771770729, 0.78339891410866491, -0.43934509767818097, -0.97719581911357867, 0.40751572103937805, -0.35369233541606532, -0.68595226949648713, -0.086738037442026114, -0.49823600984118138, 0.64732377652035389, 0.041972865807914886, -0.11177708710397229, -1.0235596278530872, -0.28556453371627405, -1.1018183963659398, -0.68560781854017661, -0.48987410807254322, 0.69674864631012379, -0.45414814849387858, 0.28679254897725709, -0.03521686248776662, 0.57846582402368785, 0.020095554318858497, 0.3481154643418119, -1.0432575927730523, 0.4908413640034513, -0.2483141751479141, -0.33092157526280624, -0.15649359844794267, 0.070982025147117767, -0.25984917429805238, 0.25080608313953412, -0.51791532075280589, 0.20935213172192713, -0.19921506770936218, -0.34752542624872412, -1.2401056679660083, -0.23799594238053473, -0.10671555805014127, 0.329514702053955, 0.23960701490453873, 0.58670600799482164, -0.64152929990671004, 0.51527974765915252, -0.42145496672723365, -0.15485711631224708, 0.26434737809512654, -0.75768306265701357, -0.81179959048528239, -0.28303718572565306, 0.43497411002538999, -0.64719379453110781, -0.93467434751634204, -0.17628530885932089, -0.045790841929602547, -0.98495178338981892, -0.14239677455992122, -0.9148694643106654, -0.53127411858315343, -0.30879801961935999, -0.4751564252485963, 0.2353993544512398, -0.44080714179734981, 0.093141182720434576, -0.47304973840428632, 0.18213637243854572, -0.24668992450805882, 0.69896316644798628, 0.41503927252949224, -0.1946022251136367, 0.69767168354895792, -0.77573968895617995, 0.55910785211755287, 0.25265111055818779, -1.1582768163794628, -0.30557930317188892, -0.45746346921073811, -0.6414727826529224, -0.31254185333437678, -0.79712595200197989, -0.085575406188958578, -0.25257291012540078, -0.84506292236054603, 0.38011464188131655, 0.56242994427055615, -0.053979819791371973, -0.21409485312549087, 0.83975286865234067, 0.64873268824916763, -0.50237934938965123, -0.40864561960177481, 0.50992879881959685, -0.021870738264235613, 0.80247908644775978, -0.03667842258716475, -0.84271424985874155, 0.80652557314799866, -0.63987839557670667, -0.039913550660685068, 0.10979551638058378, -0.46965951289476143, 0.20586590133093499, -0.23545420588700738, -0.19552696898474281, 0.44121121390095724, 0.45265751239582924, 0.50675641656739101, 0.4984792902999578, -0.57474610660537551, -0.35520031681317549, 0.47883466231088095, -0.24397358894053045, -0.40237923522247693, -0.51206281441727286, 0.39153240614803764, -0.24535790636558613, -0.93258945264652238, -0.50751388801820729, 0.34966138497108262, -0.82536967923125437, -0.80876955480080215, 0.34192022660879245, -0.7823593807566368, -0.89183808965742084, -0.45727232073485724, -0.49229404868766913, 0.72612032062021759, -0.28035261671553474, 0.067034518866610174, 0.81850606444738783, -0.75455659775621997, 0.81008685968251937, -0.77604155804321973, -0.58436616707458999, -0.9029969588460609, -0.84100982166486504, -1.0103944668021334, 0.51144712290681082, 0.78547897142022094, 0.51217741573363929, -0.46864615268388682, 0.11228883433072129, -0.72727531090555386, -0.3098557350291366, -0.97294226721565202, -0.46867288235126148, -0.05756639279619255, 0.80478564820049991, 0.44736678023514842, -0.20548020867039632, 0.96084015595080097, 0.18121401435900847, 0.11282103876478933, -0.43053320803148598, 0.32263227109918563, 0.71767244294794919, 0.73274588870788282, -0.91550671272761097, -0.79676549362041338, -0.73478400845412273, -0.46891868889142219, -0.77191371722904945, -0.51173123508025253, -0.51804004796843628, -1.007235117579292, 0.12996876118152401, -1.1139968930633202, 0.019168014296319688, -0.37906121273731658, 0.72662088687959336, 0.5382639172582635, 0.13166370927736354, 0.5556477122292105, -0.24326385293311922, -0.60827795282410846, 0.66841028306640904, -0.13348848103195288, -0.49607313606196229, -0.90070964729294001, -0.069534924000107773, 0.031490098771135282, 0.78552531420111515, -0.33884229877476624, -0.53610220784513163, 0.28556202604927605, -0.52628702656607584, -0.78982615366101283, 0.6533472740646602, 0.044204506010274772, -0.63048223425998418, -0.30487007137602629, -0.93550919213965067, -0.74903398186708003, 0.69413757328145254, -0.79083707747892285, -0.2480972586561267, 0.41246478523258395, 0.44093563977212552, -0.43873875837829707, 0.42013590703825182, 0.05917255701320677, -1.1279199959074295, -0.44656806315853809, 0.29246581034180158, -0.77222849522338322, 0.45035740923816697, -0.31897634620121251, 0.27586012132751137, -1.0107686914729108, 0.20669817490836923, -1.1832609636103364, -0.86361442167570945, -0.78023708302423389, -0.75099468522060175, 0.51594511627214412, 0.68942623535232306, -0.35776557995343178, 0.25088303146997087, 0.034850471748630409, -0.93920131331481793, -0.56484700486242223, -0.6767646057673623, -0.88989044337697853, -0.72534915590927773, -0.79387861365249457, -0.75930445853702733, -0.18441811637104022, 0.81513219040447749, -0.36355388244902376, -0.5620429663484271, -0.52928981942822861, -0.31912349382797639, 0.057045143995822931, 0.98940222627185836, -0.47430600379845483, -0.94721135798054279, -0.68078548375118009, 0.81801499748851525, -0.79299938002814607, 0.47977805545543473, -0.96205944441158686, -0.21715688830438984, 0.51245218795860314, 0.40071603745427131, -0.55134437773764922, 0.34143178837300869, -0.4995347572417943, -0.73735996103008405, 0.33076665671269467, 0.13779918811801029, -0.34176486681827556, -0.42529170868736899, -0.75031233487096194, -0.00078721109513096659, 0.36803159328254498, -0.1836271671389699, -0.62545009447220534, 0.46365388528803619, 0.6049437341452546, 0.9422260324579339, -0.54381486268451129, -0.25093831914839088, 0.37049030546651612, -0.11187986277239267, -0.14476063494771158, 0.65472223045290345, 0.82542828044294092, 0.57481048914584865, -0.88611861631274702, 0.45853082889907038, -0.34715390432673165, -0.8658109960841065, 0.77702059282319036, 0.015242424376990199, 0.10066217112439731, -0.87611736248871808, -0.77485025384885131, 0.10608809864889863, -1.0259781996723063, -0.42846569762140918, 0.16904184401848835, -0.18997937584820646, -0.46006208038248536, 0.38357646130128487, -0.26549391212082746, -0.048483374618899691, 0.05845767781299531, -0.18642061321691819, -0.77335556863415611, -0.62418050774815559, -0.9764083433844809, -0.46356087596482681, -0.13124999605497123, -0.33653203922016744, -1.1153086484522621, -0.58503820767271975, -0.44236395724710204, 0.62200178622311098, 0.33259765673703745, -0.82787358125041088, -0.85965835151586489, 0.13562054805117821, -0.65601150405772213, -0.95074189259538622, -0.6150537919583362, -0.64100716013629155, 0.56360173126741109, 0.63318703455298841, 0.30379912534746673, -0.757624465587725, 0.54165840012177091, 0.24252151219620063, -0.96965362941233812, 0.67897773818462925, -0.066744941647122927, -0.030066348283783621, 0.25102456258620531, -0.4377235504773882, 0.37074559511879235, -0.84929663414271195, -0.019914715556874386, -0.069456643715613026, -0.80517745935795948, 0.29703809002333104, 0.012620387495076693, 0.5942317984179647, 0.0042013676321449502, -0.25528631783706773, -1.1469783890587375, -0.8310792643769922, -0.26812620697471073, -0.13636205818249039, 0.14489853229775898, -1.1582304798768812, -1.1573824275425764, 0.033470854861495397, 0.39655927304240141, -0.6107766827307638, -0.13914537972471663, -0.21429587044207529, 0.91818019685780239, 1.0878060580279221, 0.40859453382885952, -0.080279065409120942, 0.51794478116562259, 0.34516852278978388, -0.97724405234695999, -0.038997057625242623, 0.65949621648841295, -0.39135305414549404, -0.24829147119185277, 0.5717981085640419, -0.67862851055849993, 0.45648067113144469, -0.05667990715176599, 0.62827365500813881, -0.13145531462371202, -0.25278352053740172, -0.43706121892967659, -0.71996812365321405, -0.026304529141293151, -0.13627869646860841, 0.32530223905553363, 0.27565556893394749, -0.048496000471975546, 0.49258148727457141, -0.18874610231114902, -0.018715658579088079, 0.22777797807932015, -0.72087327140231228, -0.15480442117601653, -0.15447353552287704, -0.063226953696617821, 0.11620299677156098, -0.23589202135297951, -0.84084310064080503, -0.93065819531411376, -0.055321083650179514, -0.80969382167136694, -0.50591633932944635, 0.51492500687843668, -0.49064326973654493, -0.21506217277135004, 0.10067783389275116, 0.5950818013767839, 0.91403066386297693, -0.11836485093110456, -0.43982062942108952, -0.34348845221938196, 0.40190867671650848, 0.10922790162256975, -0.010237080658776007, -0.63177626024776057, 0.3946950322756933, -0.6884220509210115, 0.16925597062999517, 0.81274736591288532, -0.40636120844604523, 0.62331152437218595, 0.45633646769242364, -0.66590166595590572, -0.88084494707635064, -0.35051115979393155, 0.39437630472575075, -0.17496828146675544, -0.21040130719937905, -0.49864097626123832, -0.17257514621626857, 0.33717484633890871, -0.20496102587587964, -0.40902150578558927, -0.0040656053360326695, -0.23289326169589422, 0.98553942087370983, 0.44029173068380206, 0.91798162651825499, 0.38210379301358482, -0.024400888774065554, 0.91314527904109422, 0.69511811837601378, 0.27980521532511587, 0.80495097936910376, 0.58759047373384543, 0.54577733106392035, 0.54063436557676858, 0.34862826232424782, -0.12370440945240645, -0.94712496557683712, 0.20524802090970817, -0.087202059654946443, -0.1266293493979497, 0.41523190501303808, -0.87286494166783524, 0.093524757251543619, 0.14250710291975965, -0.75900011525075672, 0.39294641935263364, -0.46103382436119256, 0.45364882636206344, 0.62867699141602673, -1.1011152195175722, 0.26559888891317301, 0.57530651119017195, 0.07713988005053149, 0.085217240876027112, 0.042449406140144558, -0.06865833301482438, 0.094278522133330697, 0.26015417748981678, -0.55381020948236426, -0.21757538567218981, -0.22014485685417526, -0.4011404830249099, 0.26805961629890673, 0.030793674631318615, 0.46770219276262087, -0.025740186620462069, -1.1335912739743212, 0.14392317181040662, -0.7898507034437019, -0.30039327470862143, -0.70807292356569262, -0.13773146026392918, 0.52477830543006487, -0.9620657904548725, 0.50304906705705799, -0.68310664863242465, 0.28418387080192631, -0.87580709283595548]</Parameters>
			</FullConnection>
			<FullConnection class="pybrain.structure.connections.full.FullConnection" name="FullConnection-8">
				<outmod val="LinearLayer-10"/>
				<inmod val="SigmoidLayer-11"/>
				<Parameters>[-0.012309978336662199, -0.051733626331379449, 0.21322191876135987, -0.017125542778162934, -0.038424792144607547, -0.0099000957496424187, -0.052243693037580897, -0.031566790161789079, -0.041031781072282329, -0.030771228414987761, -0.089394844587376468, -0.052711773995319955, 0.062377365631263386, -0.041426996628476633, -0.014602588992397711, 0.002280403903079555, 0.55158505895893617, 0.096424273781634748, 0.0032844753607334902, -0.025933396039284653, -0.037098574994201543, 0.11657780568548434, -0.012495813354944662, -0.054166102123527037, 0.047597569220390754, -0.050366318023299689, -0.037592827770209156, -0.0020815791771495846, -0.041929830721133564, -0.038449320625813792, -0.056165142221680675, -0.023825397012351854, 0.071283936946948706, -0.0036678103511035101, 0.75898496891574363, -0.011444760976303713, 0.0025950479500276183, -0.046568272570612225, -0.052188802772637904, 0.048361607427448147, 0.09727070831328774, -0.042114345121270345, 0.0076405012976991935, -0.008859639036816502, 0.04963244590719796, 0.34843931232966524, -0.016205876049262824, 0.142632529781753, 0.75680259674337891, 0.08098267367909677]</Parameters>
			</FullConnection>
		</Connections>
	</Network>
</PyBrain>
