<?xml version="1.0" ?>
<PyBrain>
	<Network class="pybrain.structure.networks.feedforward.FeedForwardNetwork" name="FeedForwardNetwork-9">
		<name val="'FeedForwardNetwork-9'"/>
		<Modules>
			<LinearLayer class="pybrain.structure.modules.linearlayer.LinearLayer" inmodule="True" name="LinearLayer-5">
				<dim val="43"/>
			</LinearLayer>
			<LinearLayer class="pybrain.structure.modules.linearlayer.LinearLayer" name="LinearLayer-10" outmodule="True">
				<dim val="1"/>
			</LinearLayer>
			<BiasUnit class="pybrain.structure.modules.biasunit.BiasUnit" name="BiasUnit-4"/>
			<SigmoidLayer class="pybrain.structure.modules.sigmoidlayer.SigmoidLayer" name="SigmoidLayer-11">
				<dim val="50"/>
			</SigmoidLayer>
		</Modules>
		<Connections>
			<FullConnection class="pybrain.structure.connections.full.FullConnection" name="FullConnection-6">
				<outmod val="SigmoidLayer-11"/>
				<inmod val="BiasUnit-4"/>
				<Parameters>[-1.10583040684421, -0.83447287371225354, 0.17089419381743237, 1.5451127342019932, 1.9360244673065135, -0.9350492820431543, 0.067321556645695058, -0.80513556492816452, -0.42774389149079489, 0.2659131073210268, -1.1191270054602187, -1.9987165712395194, 0.06865359466183947, -0.34212117469586623, -0.9287427497052072, -0.73994377314005588, 0.8141258203142332, -0.47040836697223065, 0.21349004836703001, -1.0377786322584848, 0.54771699462383139, 1.5944544580205868, -0.96073042461754199, -6.5724774412835503, 2.2628533610350154, 0.41624067010689286, 0.092128802670198282, -1.2343669896731644, -1.3134721801823273, -0.26362463834268474, -1.2178366097127455, -0.75379762545549567, -0.42660657151350123, -0.77372289765807378, -1.1126171562696343, 0.41498703841544632, 0.4362006569381619, -0.41950819286072599, -0.11136268817349858, -1.2813788105489254, -4.4974996716817373, 0.15789280426510632, -0.20727653349023453, -1.0220103140900305, 0.55523315754051894, -2.5516409267936617, -0.85239702716964605, -0.65817333740066708, 0.38167992766147013, 0.40769712186364154]</Parameters>
			</FullConnection>
			<FullConnection class="pybrain.structure.connections.full.FullConnection" name="FullConnection-7">
				<outmod val="SigmoidLayer-11"/>
				<inmod val="LinearLayer-5"/>
				<Parameters>[0.32860928782816906, 0.26507124772425472, -0.40871141816042039, -0.23870585944954434, -0.60389660592848726, 0.22814058216498342, -0.055050774472669664, -0.13193132699715512, 0.24006495312296594, 0.93191118825518748, 1.342315558861094, 0.98906338048798192, 0.22941615979403318, 0.032659941716149242, 0.14010959936687897, 0.59189287837446292, 1.0790667826138569, 0.46817226247768112, 0.99769986699463942, 0.71207839443361798, 0.092650566639659315, 0.042590580553264833, -0.756876312312594, 0.86397121496779805, 0.78401161892796978, 0.97313097876841492, -0.71740044341980724, -0.18145550030879892, -0.19559158531949139, -0.28025408045601063, -0.52150443030102989, -0.13859347176903244, -0.73801123377063849, -0.25620569005907579, -0.15174421945016101, -0.60186756485420467, -0.33258946707151638, -1.4422025329582295, 0.0061269483616030228, -1.3392541751965186, -0.31316366103115811, -0.62953481966279778, 0.087374488824294758, 0.60723246915824403, 0.20567285568751001, -0.87822087845391505, -0.092453363091903121, -0.81013347373079503, -0.75089535012541975, 0.21907834824640326, 0.32089621747966607, 0.21689095785509566, 0.91218239565244752, -1.0025696194288287, -0.56596843275459141, -0.21159072997230488, 0.060247400968740421, 0.81262267325108961, -0.13948232250359369, -0.029871143797541154, 0.69813831027389661, 0.50334953312372732, -0.86020012324436079, 0.64841027140030882, -0.37202690455096521, 0.091798525889307619, -0.41675982276424484, -0.062906375130675971, -0.32289768461234586, -0.99379104310232225, -1.0443562785422438, -1.0208557320114779, -0.91359640588219926, -0.71103781698605839, -0.019165694288034524, 0.24562206543561538, 0.08933958757956359, 0.51529691027040747, -0.48939316116106363, 0.21159568630591488, 0.38005190581151049, -0.46472253176217637, -0.054528970629032204, -0.79794426426073684, 0.38149164180108214, -1.1955263104453397, -0.3814427919686621, 0.84201043440659618, 0.32107367945631943, -0.1607889636947426, -0.38317930462065081, -0.83215042949091722, -0.61911703522823058, 0.16704461429411344, -0.23281220427467111, -0.35688472854704073, 0.48108620810434405, 0.421991557737595, -0.54876689445904225, 0.0052831754254557646, 0.048300020187081336, 0.61976772318472551, -0.97101824172937223, 0.4303543413307554, -0.57484682096069506, -0.90726998065283126, -0.33088696659068456, -0.36979874281671649, -0.52436778233384695, -0.39767937572928236, -0.25265042912242419, 0.0059364948955186111, 0.021654348185295387, -0.70918852617994665, -0.77420111938520952, -0.35515243826241993, 0.2354669788105582, -0.73524863866186196, -0.49511490012312898, -0.90666554121585097, 0.19113217948482875, -0.91982013520124162, -0.57803076641171147, -0.81618622796489293, 0.22698949259196533, -0.23228190914311561, -0.35180453819341034, -0.32302097821756981, -0.094719391649746271, -1.056282567176845, 0.85335342445385154, 0.87090081148266041, 0.36533965324229578, -0.039730221822620759, 0.18825714327537973, -0.082287069191743625, 0.11900477340623181, -0.66714775660197356, -0.26955402934847378, 0.44384837881752687, -0.16459909203908249, 0.64725680845114675, 0.41693850268899019, 0.21292871622858398, -0.16420128640270917, 0.4546470765266154, 0.39995202086414922, 0.083802448108695651, 0.38188006044387351, -0.28358008369569621, 0.33205772514557091, -0.90124348169516488, -0.17277153941072812, 0.26753411272043576, -0.55497388343542697, 0.85799299288326314, 0.62936323661826543, -0.13149194017274327, 0.85397148556799141, 0.047425465309171771, 0.47459974803775001, -0.062477784266758311, -0.6963012599279047, -0.63848914071414253, 0.67508582790394278, 0.17882001924985752, 0.82301618649159169, 0.70645764252239551, -0.132432490372071, 0.93115644681841891, 1.0900728257839791, 0.78480324983499772, 0.75479441359171362, -0.94399611839001518, 0.13081585641464683, -1.0062150887866919, 0.85908449338962034, -0.96876596684586691, 0.54085207977038918, -0.87425702002000372, -0.83804441063811197, -0.017930411889986019, 0.35620868332176142, -0.43766564275424868, -0.34140616598012019, -0.5796946381729402, 0.78479034141404724, -0.82870911436474282, -0.82865410129313322, -0.83361277700451764, -0.79032378592833885, 0.49639120136764386, 0.81150124343339458, -0.3590702207709594, 0.75845931394604982, 0.29840479628791156, 0.93253131354923013, -0.0083138156709291998, 0.31655024300870421, 0.6180062395748227, 0.75099349201204346, 0.51735686294955141, 0.32937994040895929, 0.00091365265082193317, 0.32958617544336755, 0.40203655903404689, 0.26208572253560131, 0.12975799197770782, 0.67879774933533665, 0.233201557391187, 0.98870154935386456, 0.38309427565309473, 0.17273794873457507, 0.60450946003827211, 0.64832646053272103, 1.0125386214773362, 0.5613587876084325, 0.27331971475229871, 0.90888360594540607, 0.57297946255871668, -0.48423258716046252, -0.81160682290106267, -0.65047081354743541, 0.44707855503570093, -0.65564706423193309, 0.20035181819359973, 0.64819257935372177, 0.20749884151305997, 0.34224540571155238, -0.51268218989373748, -0.068270953291021633, -0.24970857585755177, 0.56920762160901173, -0.65907006364081733, -0.12426933423720579, -0.32570259737004215, 0.12239791179170992, 0.25255741874090093, 0.93063197310949275, 0.14930466926716993, 0.36417602544125394, 0.42691132055336733, -0.85182742491558683, -0.61378389011772616, 0.49264010437243011, -0.55122574871922669, 0.34440159451106822, -0.74127933859676132, 0.2749183101544434, 0.83375242937329197, -0.24328609043226387, -1.0676987485858473, -1.0590387630154388, -1.0217400637663008, 0.10126130691308986, -0.6304485766373501, -0.7980022829324589, -0.43300214178624352, -0.94809439298215581, -0.23841008729477778, 0.19963738836925712, -0.75229511964190865, 0.41912853032011066, 0.60282717342778613, 0.19674852722510427, 0.086720437982332171, -0.76372971403400669, -0.58905559140487396, 0.6986287436411055, 0.058803087253053304, -0.065196401688787917, 0.083910170099829665, 0.14050174408340363, 0.53444971574585609, 0.36063249609064124, -0.8277133000248279, 0.488260038170102, -0.74113258786623115, -0.57596796276834172, -0.19630270724339996, 0.48312359142143463, 0.43404627335705281, 0.56329961933395156, 0.37384762741056099, -0.18158400224418858, -0.012388766809802568, 0.6219325351946372, -0.62635301861567527, -0.16090846135562806, 0.27871216546052785, -0.70053020377830888, -0.20553504113914373, -0.75072218745937414, -0.54144382422588344, -0.63328498337093375, -0.34077926363407529, -1.2058745410343796, 0.13547950102164732, 0.049766658535260883, -0.90651220041617597, -0.2211755496938618, -0.35526775767083385, -0.018182686727591525, -0.9406371211240413, 0.42550176574126408, 0.54191119770433238, -0.15207736709939074, -0.82615196600753504, 0.36761978722008898, 0.49924518353153108, 0.32970314182005406, 0.42685111611575682, 0.31799422397970806, -0.4599263356073226, 0.27531700486584954, 0.51523768242734613, -0.13469762169671023, -0.46692098422438499, 0.55110003904503113, -0.5362033968898009, 0.64300228860862252, -0.17324608613273346, -0.57550017254094754, 0.19572234805791058, -1.2750257888191887, -0.60380847258494386, -0.33680078258592766, -0.85110476501744592, -0.42242710045203141, -0.17564222719411837, 0.059222378959302623, -1.091127023895712, -0.11834082157691588, 0.11063396777474459, 0.12415601391422859, -0.059354267201442122, -0.078597885994252367, 0.18114360514907527, -0.7319285920259625, 0.41028278870770329, 0.668628626512073, -0.63763837839406334, -0.45420201595343868, -0.19421615215136834, -0.47325739990957089, -0.52822171153045316, 0.51352007000879163, -0.32010514537491025, 0.040174766596911882, 0.10242096346704539, 0.0033333418527080124, -0.44765962309014368, -0.040034440377011066, -0.24077522192494366, 0.18312311241109883, 0.039433157086019695, -0.12845237897112649, -0.082656173543795633, 0.046261421858352476, -1.2520384682088304, -0.30925145098977036, -0.0033210186659596219, -0.18646099232404006, 0.043647637908894872, -0.07641172990834319, -0.3245587405810097, -1.3639904035363042, -0.24595923630736061, 0.0080305826298864031, 0.27661923642790404, 0.30038378127495241, 0.3481099859077097, 0.14085876838317299, 0.14894072686147067, 0.024963962260274357, -0.003746253488884179, 0.12257008853814177, 0.20024955591227425, 0.049849443697245865, -0.10096253321645131, 0.32539629998599712, 0.38449293062873596, -0.36088553288940495, -0.092768870968893191, -0.077405745631655809, -0.36454027461446092, -0.8822551484431217, 0.1611107113959053, -0.23162010831633625, 0.63492601233983414, -0.80032432183851587, -0.79556270651398375, -0.79179810096744407, -0.77620301695479654, 0.62640945830047956, 0.60337976128386461, 0.55553499845838283, 0.47685274324226951, 0.6366868236785671, -1.0213006466704895, 0.56811877862938276, 0.51553640077603413, 0.51072401086101848, 0.62453014655499806, 0.57501196997637571, -0.32545152567928587, -0.31417770652917582, 0.13794792831493621, 0.54110102584886888, -0.093713750752070155, -0.52674984886728093, -1.2098814097369675, -0.17029229958366998, 0.13443837419620833, 0.23439497344488305, -0.71593961896113922, -1.0049210516536029, -0.12257830664418495, -0.41992412885082769, 0.30248721352212676, -0.31746148703572519, -0.61958241376643386, -0.19290318059887798, -0.24972644549560097, -0.59679687648742319, -0.10613977573539533, -0.61713495923690487, -0.36153347600267505, -0.82362083461838032, -0.75403463060061204, 0.21558010819704476, -0.14244389155524262, -0.035171910999886272, 0.10670106619224839, 0.66476186626277456, -0.95391723455586186, -0.90633853248312191, -0.5565034462113192, 0.79624660687674476, 0.86691864009154118, -0.7678691468528176, 0.44501637487548229, -0.91374002716319547, -0.77435496027188355, 0.43284832921541683, -0.62095213416472406, -0.39694735121827263, 0.57464655064219627, -0.53385062698762009, 0.29025809445970074, -0.1573005229514447, 0.32564561395277275, 0.19500516378965804, 0.11760205308988447, -0.70152234408201786, 0.2293962368024369, -0.45118216646198323, -0.98205777079250078, -0.30102070027631012, -0.27648672301470167, -0.78719008863390871, -0.58762333503448916, -0.71123365728746268, -0.45784680486554408, -0.21123971994475105, 0.10332550700405523, -0.15663093781724086, -0.3425383000464518, 0.018887754273942538, 0.2320851757023909, 0.55067439644882166, -0.068371550836266184, -1.1194582361780128, -0.0011053441945768714, -0.093368645086444144, -0.069310815354064567, -0.35620474221756049, -0.069042204023862713, -0.019952317926921398, -0.040073054399054606, -0.33968549362032258, -0.12791462337693493, -0.41614876708172904, -0.58367573852751953, -0.24718198139425962, -0.25343731742450298, -0.42150457331341357, 0.094979822410975648, -0.25876961828741235, -0.32832734690106968, -0.47508566019012388, -0.46738797007484978, -0.19342446189496149, 0.23204240896920222, -0.095434308352331645, 0.063037469711517191, 0.17303674555663204, 0.12705827406399606, 0.22736515664536988, -0.05672037466261004, -0.23678424164835854, -0.38166381630112722, -0.025180836187816986, 0.29456955656915534, 1.9300340039371275, 0.2714281360723384, 0.036523833101029753, -0.32800315630971466, -0.86490868797847975, -0.18779300234348043, 0.2451715459744952, -0.42448135150451977, 0.32618273398150538, -0.18461785327758162, -0.78443901923279236, -0.00507049783345348, -0.61197473262966384, 0.59592299300592178, 0.14838958809315295, -0.46123039329281024, 0.83914842864417249, 0.21357051604357338, -0.16714126978367555, -0.1840919017580753, -0.74742137507385809, -1.1207681999113037, -0.0033124826787554427, -0.95520298518223135, -0.75241834443119948, -0.86354892587392806, -0.5078507117268346, 0.22323056787493231, 0.41407596567236915, 0.32864290064897345, 0.54775913081360428, 0.41985817860177427, -0.45750270563625484, 0.15592151882652594, 0.26277550893673235, -0.24055792352091432, 0.15358788613010915, 0.21374900658944118, -0.33724615461895024, 0.45315508270170479, 0.27803679544767756, -0.2518701243231552, 0.24305961707264997, -0.72728044571184935, -1.0156876508981425, -0.00092991422950787831, 0.3078235235076725, -0.13820465941598231, -0.58379422455701946, -0.48774318951293, -0.98602067544920191, -0.53260867081242114, -0.50395733474500715, -0.45575602473365806, -0.50563908949693781, 0.17030189851942551, -0.45415316309494891, 0.28793490694001794, -0.34715628434132406, -0.071015062409651664, 0.53248796045569835, 0.036018760591440102, -0.53612541850911888, -0.010718157328329708, 0.69415520505091288, 0.44069193186043665, 0.65419330816031618, -0.068198203240978264, 0.44217231748287067, -0.25040511528844239, -0.69232058636116345, -0.92612483160240511, -0.40260423494183295, 0.66536440617874726, -0.16159336506379599, -0.4668033136562329, -0.40047992649186254, -1.0195985700395835, -0.83546221956136235, 0.68234245581261677, -0.77739562217303293, -0.4918414271219031, -0.90427771507251931, -0.13101593925423791, 0.46310039760541682, -0.3760452271991967, 0.058598350203686554, -0.62672960938920541, 0.17550929651734662, -0.059787361559263286, -0.28958739130251532, -0.63118025009103396, -1.0564979842136355, 0.12827883240263982, -0.166141285281177, -0.046231433113582354, -0.18389187902677459, -0.66252716422244673, -0.76507632232450329, -0.95581507776108243, -0.79167490669818896, 0.80156951825703948, -0.81958226115031885, 0.90568692712761734, -0.9568844518843842, -1.0098135659568019, -0.20287228452068726, -0.12627903282464825, 0.16410433541533115, 0.16724319278873315, 0.26926415971393181, -0.78320538168117781, -0.37519839558088719, -0.26947509440509976, -1.0575238002427643, 0.14707892417991, 0.53598205862646842, 0.31087477529058072, -0.07492292787285483, 0.24347280244103503, 0.39144948830186926, 0.68308116338046521, -0.24595298374662009, 0.66108418354450382, 0.29333870965940223, -0.84105662222732014, -0.60480309433221702, -0.30736207184695419, 0.41661632716696001, 0.33907123383332249, -0.98174511709096401, -0.60730356304320943, 0.47516821169318796, -0.26232213159545126, -0.86094726580773695, -1.2063538892203476, -0.10115653360092869, -0.59565582300903352, -0.37052595344770362, -0.52265162567287082, -0.10993539869109104, 0.37667432944781287, 0.52394376561511646, 0.27368224182436424, 0.013158177270317074, 0.34908386024554278, 0.60212734622180242, 0.4472867743541134, -0.74222747333842753, 0.92157157896026654, 0.34623278767683197, -0.9233666367027854, 0.31405892752412712, 0.97759185388391645, -0.72572735152936341, 0.045998804495728934, -0.43977644556967826, 0.50686589852479291, -0.7353113922365474, 0.57882238368840189, -0.46141564367373517, -0.047862980453133447, 0.11181694265293765, -0.023853550839737107, -0.78343296604356039, 0.66398870724394621, -0.81717250079465364, -0.061541191508717827, 0.1922641168821658, 0.13713029182417713, 0.36518590426272268, 0.26682599302435839, -0.9162644467074218, 0.2493947347229469, 0.34207178154900114, 0.12581143024873614, -0.34306852088264445, -0.34555653818928661, 0.080858542663902161, -0.78751932986073747, 0.033759905034634156, -0.33712693910909503, -0.38076440963512864, -0.080238116978619808, 0.40868185024906095, -0.049216042143475566, 0.28872305410058902, 0.088474860103062394, -0.13682015809968157, -0.54625450872112102, -0.21892248883922555, -0.15576525430830379, -0.45651874341738441, 0.029330823923613795, -0.58180040908402797, -0.22601960448181874, -0.096532471807257686, -0.037740972592178457, -0.24868364535344623, -0.19493734645020433, -0.60519573003818528, 0.18795161064930271, -0.39046964740604445, -0.32107848532284156, -0.15632563392403509, -0.7054046342356346, 0.047568200912490685, 0.17253690291875731, -0.12489830637333385, 0.11386985684642183, -0.16620998579294563, -0.58912782815906684, -0.084383888295503542, 0.21821788657057209, 0.23385216917657126, 0.37465892051471916, 0.23658897429153894, 0.26161395797406733, -0.057368603250845952, -0.34718391228587459, -0.98195445009745574, -1.3086593759153893, 1.7689604709442688, -1.3599350048614762, -1.0203545000305034, -0.4075323981825319, 0.0019598482414052479, -0.61595094231785741, -0.29493722539903333, 0.10263751165178961, 0.67418444439060143, 0.53040508388307894, 0.84936523481145754, -0.58057701445553322, 0.71166880728266857, -0.31166293943425005, 0.6041309326201898, 0.58084449468534072, -0.6925346464420703, -0.20578986864726012, -0.44212525793117374, 0.82496732701487296, 0.68394335553501695, 0.3959064796621381, -0.25937616100094241, 0.43457900592180504, -0.76130341702245152, 0.48495514926811772, -0.072140308512066806, -0.65235775122928852, -0.64056596552885359, -0.90638293161863293, -0.20308366618245952, 0.53380031081890389, -0.41643546648795132, -0.79526558295210747, -0.5119552167184257, -0.31399224459649244, -0.14110717122074856, -0.29258092892488291, 0.096729850355653277, 0.016155667057580276, -0.86123723170892619, 0.12540635579179316, -0.34597790962270014, -0.11290817882751744, -0.037982515868142837, -0.0715200850774107, -0.53750659120720568, -0.77835428776576643, -0.70191915498108426, 0.25326581282028637, 0.92410822674221316, 0.20227697440913167, 0.44593608088155018, 0.51284644078095498, 0.81027449671860374, 0.35546714415417735, 0.5995720816259954, 0.52471943583209268, 0.014254489611174091, -0.83845370412155618, -0.58594232021655679, -0.89348828853590112, 0.18107268183086303, 0.77914910136094051, -0.55600627798083968, -0.056742489679774577, 0.27416312629498113, -0.27470104272054213, -0.73223484960750485, 0.41154806102291897, -0.12350475299977307, -0.90100132884112216, -0.35967015391126406, -0.22749258072064552, -0.65905329061419704, 0.46728080820178464, -0.20888798136378764, -0.95626834946962092, 0.26520375829740489, 0.11810243037314649, -0.71791471364535175, 0.075377241860483543, -0.91392568042067113, -0.76675925917342058, 0.51662235952701707, 0.060449312072908497, 0.10781637360311866, -0.18954177103984485, -0.54278276300635442, -1.0949456043351047, -1.4841252711713195, -0.22214705074245358, -0.83600374497145824, 0.43152109771344871, -0.39902501095325438, -0.48418214758983458, 0.26679689771123971, 0.6898512913530388, 0.52185021782140983, 0.42195713797538897, -0.99455195457228318, 0.44988986574304524, -0.73695553832323069, 0.64343571248621889, -0.997351194892795, -0.58569411741698041, 0.41918991060213873, -0.48753936253998115, -0.13325059432690359, -0.61469077449800946, 0.63463600518041152, -0.81921050054898015, -0.31669314775386426, 0.14916851761263883, 0.49243624779556977, 0.082028189033494806, -0.48769793253868143, -0.13988196034376041, -0.98621505415363975, -0.96115051694813813, 0.16031763336440674, 0.028404179375313938, -0.48282551382226152, 0.39962662474674071, 0.12832582997182063, -0.97115678423347462, -0.15388227478036393, 0.034161457452109717, -0.25205917830166713, -1.4552724081105672, -0.064353864386312673, 0.13245436404686875, -0.77773581666001856, -0.19195015198419399, 0.74166755478419877, -0.055671026236557737, -0.38057531300826064, 0.38311200352210345, -0.61526826712370553, 0.13519172236614538, 0.50354082529756294, -0.76478063132956564, -0.37231557374801239, 0.055800182229925055, 0.74465428160473679, -0.14231738116202847, 0.62683056066603338, -0.1051245341975412, -0.077841801012332082, -0.62797064073042108, 0.61926598936974453, 0.06483595163320606, -0.51205106956841429, -0.17637964232549783, 0.22098936737752595, -0.62862819521236335, 0.14113083226261791, 0.66847790557327791, -0.049605882821283351, 0.36754788261297366, -0.64121969523652744, -0.1909479512506064, -0.78908083809881124, -0.72347337459718619, -1.0171163078566332, -0.17288503235769995, 0.47537722688248557, -0.5603699027827902, -0.044884108255716496, -0.0073443139210774598, -0.38567273549167153, -0.34083121791059773, -0.47894303775281327, -1.0439764214787737, -0.61754870410363694, -0.11735403046100132, -1.8433225377413516, -1.0029431219650851, -0.3442373319639383, 0.44857988051360426, 0.083153164479105479, 0.78006246446874727, 0.26928249032967233, 0.46179623837583972, 0.94372135828573567, -0.67692694364893169, 0.072265116657113826, 0.51012771588564987, 0.64300532525207743, -0.97196930285997774, 0.26147736743649308, 0.041992676597279226, 1.0448990861232876, -0.78442386660889674, -0.014799361567417567, 0.89937719542561301, -0.28988493076051558, 0.71611785902088354, 0.75386202343381059, 0.057947463755186855, -0.14217947115732998, -0.29259715554595062, 0.66152061035900622, 0.69139995337188598, 0.49452190206090307, 0.53776972530232015, -0.49305920184101876, 0.32268192491182018, 0.11199859025757834, 0.60122807863075611, 0.56949924759625392, 0.24260365133466499, 0.37238411536178279, 0.39878044451396394, 0.59894993896202642, 0.66216399380250446, 0.60333360646036172, 0.30196951777084219, 0.093996524402368081, 0.59673783073243336, -0.50844448715463586, 0.14352167023807177, 0.52853840060462509, 0.15527989464608652, 0.18601385214138186, -0.51412808461390247, 0.67973454571839753, -0.26241257352612762, -0.33457977045581788, -0.45787717725068411, -0.62576525059055221, -0.66395887089253069, -0.19589954566766149, -1.110415775352535, 0.55406742395522146, 0.44588142261934738, 0.074638090030107962, 0.60396300566698879, 0.70685323638212016, 0.2451222616267543, 0.32811417453042124, -0.19970361708583617, -0.98716696298343853, -0.22641357860268899, 0.23120228059251241, -0.79196147048932475, -1.0983391710623112, 0.64398768927374317, -0.51816169555379243, -1.0677393154511379, 0.09490179776722335, -0.31127019389057259, -0.86036670941268911, -0.24409358451425817, 0.082389217091627984, -0.25581400702776957, -0.57505635318672432, -0.12431226910420952, 0.27278942523108496, 0.26784386541090632, -0.011828811530803313, -0.18164451567886336, -1.4615640794805866, -0.13671125810406695, -0.10921702066904423, -0.23593062417301761, -0.14318930461844789, -0.32208372569956817, -0.18777107088986769, -0.16913490064408573, -0.16892182639659489, -0.17945447416177637, -0.27345795122837702, -0.046770471299153453, -0.31015397216737717, -0.16343659335999722, -0.140730999894734, 0.0083758098806729422, 0.12187620202040642, 0.051720883560082136, -1.3460092827179337, 0.064485483836586352, 0.10085903342450839, 0.0048550946767373848, 0.2042614646709337, -0.2171771644977972, -0.28812196707854976, -0.0095920344599767556, -0.33258645120440317, -0.17940847999167703, 0.17547126617551181, -0.030410849822417083, -0.12074883994559632, -0.1853398956106114, -0.023898941946005885, -0.18442218376096911, -0.10499282888536281, 0.0060191902762707049, -0.4768442742104026, -0.96011208952597749, -1.0666332615989866, 6.4962289079959588, -1.0808246293140078, -0.95498757941137713, -0.42137642948090182, -0.069128668214414796, -0.21069140888179733, 0.5580920403324825, -0.2542063330112132, 0.25796798437511897, 0.92535671798116015, 0.90592110097281975, -0.38392505816466332, 0.52146505718899694, -0.4212510486813536, 0.60661179875445126, 0.73867207196558893, -0.8790018810754251, 0.020602541029042475, 0.25991535753032025, -0.039785986910256949, 0.23369888657443091, 0.60503901046061581, -0.084939820345061881, -0.021054010187275801, -0.060573248499183531, 0.21411327193155896, 0.071773159955357102, 0.2504083754208879, -0.11613719560239988, 0.038725866828398438, 0.3015056953753239, 0.37863729671069191, 0.016186853424174846, 0.02676329652605167, -0.084566247842144296, -0.022015551504808464, 1.0096611285535346, 0.50358288430737985, -0.11172532287636028, 0.052586086079654253, 0.12638619137262391, 0.13530676176455358, 0.39721526609870628, 1.6025759776077317, 0.8890883758380782, 0.28490015645352007, 0.19066720087102368, -0.20639597255328299, 0.86532282184497444, -0.12621215559976731, 0.66245138916171087, 0.48630121654976616, -0.43319679913667875, 0.5613146034400609, 0.66650177062300631, 0.72901915476752643, -0.8980837918370802, 0.70588836516559395, 0.26806143838450486, -0.33820227230967914, 0.89325221119182652, -0.20398274191897578, -0.74393925355321189, 0.10030914368893594, 0.18852012633539905, -0.23843399270679075, 0.34881154735785663, -0.26536891492568571, -0.67565750852444639, 0.50791637498818965, -0.46388509478224405, -0.64116184662315412, 0.66135679023520322, -0.12406333509325472, -1.0243822927894188, -0.11322815599886302, -1.0262419370732694, 0.042801028564963935, 0.21664974319750838, -0.6129001214687736, -0.18599479718814707, 0.34142381170961283, -0.056454723222288374, -0.56499683205969642, 0.2460582299387552, -0.12697691874065339, -0.59086961115314052, -0.038251574538759381, 0.51465024330277842, -1.6997899906813918, -0.14448622800559535, 0.09201285103785467, 0.42796741502055063, -0.36425604012332075, -0.13948980034648167, 0.1621622935084549, -0.23438206762338931, -0.9498460007479318, -0.40238589098135791, 0.53323974242360328, -0.7204060289007278, -0.93742911456516664, -0.54671806343745277, -0.70220812350235584, 0.88344559168906489, -0.26248435949203974, 0.016737880645934081, -0.65406595513773691, 0.31988641234586446, -0.25918062670783687, -0.6368336046037103, -0.84713491848797595, 0.65531091464405888, -0.34602870703732858, -0.75335818655608666, -0.53213706166647856, 0.22595834232477938, 0.16911372042440243, 0.14370863782441992, -0.30136098581808596, -0.20160832457622724, -0.96857723462705603, -0.27759720158800882, 0.43512864070286589, -0.14986137626860824, -0.24308344075146229, -0.41249341312896159, -0.79353651789635027, -1.1713319782064384, -0.85258590155409275, 0.16856600850753278, -0.69259568078052747, -0.16593594889718913, -0.16840381439087454, -0.75913592336162072, -0.84302281712470251, 0.39800434678672175, 0.34771150113284233, -0.69152532047425641, -0.52249983381947984, 0.35791119838377367, 0.54160794829319314, -0.18127085648292698, -0.063363756669717095, 0.060208854325625852, -0.32000256770652902, -0.75700738444412241, -0.27033695160797167, -1.0991127730545398, -0.97256630708136005, 0.77867748360799538, -0.89780609639554543, -0.18340739799339753, -0.38409331825592108, -0.010235668372577569, 0.022048316756240353, -0.092144030099937629, -0.33651322565094138, -0.45360352763394274, 0.15110619700132971, 0.29559212890786685, -0.33225132552669689, -0.15204867377565193, -0.012324057138305453, -0.57512701277081035, -0.85493699853097271, -0.049220211025119059, 0.074098418371005087, -0.065316445965970402, -0.54336484833534482, -0.21783405371258668, -1.3465307833267988, -0.14233930484228344, 0.28359791761857023, 0.24602997263184423, -0.17500406663411372, 0.19182905063937447, 0.6301725941702907, -0.1886668440089338, 0.069414982309909973, -0.088059016409558238, -0.75312291798568498, 0.0026379817289533532, -0.029612454919154652, 0.71265422470401563, 0.58214072801109362, -0.32478035848188685, -0.18525793790544609, 0.42700600609895356, 0.035930212844641547, -0.55473668789795405, 0.38593016355001714, 0.11117199832618255, -0.79808269411839416, 0.25343004334438612, -0.073005615161099879, -0.42020547097809913, 0.53624835963215012, -0.78229082360068669, -0.63566420188038442, -0.20385613724471144, 0.46434623803155362, -1.004696065065066, 0.0037740066758143666, 0.40401979609656991, -0.7785562275061112, -0.2405227445448839, 0.20225109960958465, 0.5997462163700884, -0.1578588139015461, -0.9357100006952479, -0.78482250397719699, -1.0324055728872115, -0.3383959354251887, 0.36376190796883434, 0.05343437684549842, -0.036362597783682844, -0.029424213283569357, -0.62877892513116873, -0.54623214084018024, 0.35311366130405614, 0.26748229625510322, 0.36773134049174228, 0.82932890402199178, 0.88891640663667681, 0.27967789214422573, 0.43380745339418014, -0.68984308457099786, -0.0025581815273284952, -0.72166558446385909, 0.32811792879243451, 1.0147418668161738, -0.67101870479442793, 0.83735803646939178, 0.069451993527334444, 0.16546785016129131, -0.37708440304433466, 0.41752961635141378, -0.86347383438051462, -0.082818737347764418, -1.0675269236571945, -0.091953365968754391, 0.49155538272816296, -0.38211150188450893, -0.19106017024816324, -0.6593858160770919, -0.10544387605859883, -0.54193918526567642, -0.56502994658694539, -0.51166533160001282, -0.092682016076705495, 0.017280161141790332, 0.79484242264706795, -0.41876028978393609, -1.3051406377445351, 0.025962186985119592, -0.3086381872897162, -0.30324907568451698, -0.16253508761787105, -0.36424252071091812, -0.092507862287730433, -0.55609533532129918, -0.18169749706632665, -0.11495662181168438, -0.087445315041127708, -0.69836094323527753, -0.37171672858665095, -0.16814276275614207, -0.0261411769002452, -0.691731571520945, -0.23049775822030183, -0.24507828975159907, 0.26382712384325557, 0.03037875076079791, -0.29083306954713634, -0.091772794968382365, 0.52841430633099795, 0.1968273716281434, 0.39557484507479534, -0.41172803887868564, 0.62673036760173939, 0.30760759339729843, 0.37244520363377442, -0.35122405452043642, -0.36824675437407511, 0.31110941069622911, 0.18900500593811881, 0.99816714840400467, -0.66054324710759837, 0.16913176657812676, -0.44077246846013507, -0.40210837793545445, 0.57893093073163293, -0.31798982509180057, 1.4937245487668063, -0.29975840966894374, 0.40915067354929135, -0.33178448643888675, -0.44971474436693454, -0.59122897156572785, 0.14078743126301393, -1.1902241374921181, -0.1169138296022859, -0.32302811842955886, -0.38615264941842764, 0.044533301921014026, 0.75250188294129772, -0.93945656616425366, -0.78514972265801075, 0.13874601785318308, 0.84695642918909242, -0.89121682624285914, -0.57593656781865521, 0.017600560251869159, -0.38002661423246725, 0.71456064651135465, -0.68406563424888056, 0.307474882071886, -0.81286511434959086, -0.39657487708846617, 0.075435573289624108, -0.77109948518325144, 0.50333100554083765, -0.54822133153719532, 0.45452435512169714, -0.49032453701320855, -0.9260636256908894, 0.23892758144113366, -0.47238480928301108, 0.75159292545504353, -0.36709607621999707, -0.70835834065322789, -0.13430139674823363, 0.090092941282837444, -0.50384173585903247, -0.30914220199982406, 0.68906166772050914, -1.0370425912855312, -0.25568458939331717, -0.26588738759731684, -0.11464530513544671, -0.55835729358432917, -0.12501985624758988, 0.43804082368514824, -1.1805160790012497, 0.36289419275938994, -0.49687197422863943, -0.096387894744823455, -1.0114786746361304, -0.20772716974918634, 0.36725155030971357, -0.62965522694464848, -0.75546886679499892, -0.041409664778765731, -0.15642966077890461, 0.46479139779833151, -0.1072576720240173, 0.055307969089626229, -0.51231838695797616, -0.96976881653616831, 0.18209904601439081, -0.50509360381121771, 0.78012282522875909, 0.14774197576871123, -0.44065780797361304, -0.521658150880009, -0.73798982362821786, 0.11935014658721706, -0.64731295732614913, -0.94250700851741032, -0.97491778292307585, -0.76093020266454636, 1.0289266681705327, -0.12440519836475968, 0.72880788571107757, -0.97323126494861323, 0.16907537769723741, -0.48126770241721661, 0.056471569923567763, -1.2776678584310321, 0.12094873921836459, -1.0151585533108909, 0.045300858591666097, -0.57935937134052917, -0.31032414591990243, -0.23056241750252895, 0.0051112856585147923, -0.75618456876595874, -0.27825326618983165, -0.17576088514656696, -0.1417497507525762, 0.020437598888908417, -0.20218626966636635, -0.90345282309675035, -0.76311597758810001, 0.28394281254586812, 0.094824114339370102, 0.54230997596903929, 0.3749643081025113, -0.84931700254462072, -0.88300537777240196, -0.82240952172443338, -0.13900841818805026, 0.48198337706987876, 0.48401444692068379, 0.25222005788325352, 0.23381507087809555, -0.43260854662958048, 0.11442213672527821, 0.25288511659327417, -0.78413214034475254, -0.16396921840767417, -0.38933005300564455, 0.10941342031315804, 0.30112465588330345, 0.19149945221626749, 0.47990890746836878, 0.020166330431246344, -0.70243855363539143, -0.10085376725179283, 0.1849932607956698, -0.1838824962056351, 0.2557409865512702, -0.39242383800442532, -0.45776923141818676, -0.4378602992654228, 0.4803284815878533, 0.10884873563941316, -0.30333487252557523, -1.0179961651703084, -0.2467826101183842, -0.30113188060791762, -0.97134439597117861, -1.0944724395504022, -1.1183399312661975, -0.24252557006086489, -0.48487484092379085, -0.22408943934493983, 0.15157587635804934, 0.2980564339128286, 0.28003570079106038, 0.45788606387504538, 0.45343134245206468, 0.48906880102613431, 0.1373962398341107, -0.17582217637655609, 0.0048286299988193502, 0.065907749623079728, -0.1496527537636434, 0.58674482082799939, 0.49503215600700723, 0.13937714535797316, -0.29461711532130386, 0.16790608818801142, -0.19710812197378841, -0.056995028738408317, -0.79450684880575639, 0.98663383360780965, 0.40412539080663179, 0.41606337683161498, 0.45809682098780802, 0.33149912252809954, 0.15975862973410954, 0.15293118420390633, -0.10501127086163271, 0.016064975104214552, 0.25293952068561953, 0.1717066176392982, -0.17184861320182721, -0.27385887453575652, -0.17187739393693394, -0.35539484211184902, -0.58221803737794142, 0.042934448514550361, -0.3283109168710035, -0.31260687227416162, -0.45648599654260202, -1.9465538027783242, 0.1081543834208759, -0.51691548313210911, 0.60210973243558663, -0.33517639015768597, -0.0057689938320551679, -0.63855437053149189, -0.12055887469861103, 0.37013186279854809, -0.73109508179124638, -0.34688707607929259, 0.5566518328963912, -0.76389952999315636, -0.59825163261164138, -0.67963958122849188, 0.078710738913150335, -0.0044948105676993937, -0.79457791551170653, -0.86760313887894758, 0.36645473715828403, -0.25196754117629599, -0.91311684923651615, 0.88189075299775976, 0.70403836743240344, -0.082999403836757149, 0.76770061911617626, -0.78605508617944753, -0.09248008062612445, 0.44306197352680221, -0.91020932946326638, -0.47949031825198485, -0.94141498672706525, -0.59128346740550553, -0.91319452351621055, -0.93972412709416453, -0.51276448915716155, 0.50562559355456582, 0.36079036193681152, -0.58702552892836868, -0.34657884290522056, -1.0201410759552825, -0.55207942861965509, -0.64929060983043807, -0.75641295062427805, 0.15921229519358612, -0.94242473021190665, -0.089611107886787819, 0.63758098801901075, 0.1485538276617579, -0.24680343857667872, -0.66369869506579826, -0.74557701180331559, 0.1080450156002184, -0.54578020866374766, -1.0193813116291355, 0.26110577294631626, 0.75996455845639244, -0.45452016065336037, -0.21237931655878048, 0.63069626981982885, -0.31735163453555748, 0.59630605790549107, -0.14308510467688992, -0.54233595756025665, -0.24949431976648326, -0.96150147899675864, -0.73608635899614472, -0.77274824225594241, -0.68447976824944756, 0.079386007733610139, -0.78339967041084435, 0.41550329793298019, -0.096802197542189924, -1.0156016102785341, -0.58221748492943537, -0.59058566813167834, -0.094324195924646428, -0.15671117969992707, -0.034037019455699286, -0.41363755332025531, -0.69168983101602366, -0.41852254993964477, 0.053016500965619766, 0.12527110413176487, -0.008078608772855024, -0.021363017750641471, -0.666362738228927, 0.3175565837156506, -0.74328181021684059, 0.33134344403745425, 0.60813050580723427, 0.8360951884100285, 0.92238215236929322, -0.50791926360683415, 0.51877395294431428, -0.74243521000280088, -0.0072748574890679615, -0.74916701643805839, -0.38394457055593373, 0.76030946512749342, 0.4050854198599344, -1.0075887831919783, 0.72508924406612485, -0.85097818631859612, 0.39699402351583546, -0.84300682994892007, 0.68473040972050336, -0.85753550510158549, 0.43485545707471496, 0.0086723755133462383, -0.34665680431658846, 0.66262797944802965, 0.77043363632263762, -0.37300956741951907, -1.004550293938566, -0.45310403977828739, -0.039951066826237877, -0.47160384880591494, 0.24674945102294576, -0.6187953522842401, -0.28468261796676497, -1.0098912214823166, -0.89788177716907569, 0.46354254618266855, -0.98252203446852804, -0.93298020531369041, -1.1685693930655021, -0.44856806820657869, 0.39286753027466625, -0.3271090017249273, 0.24571916237399696, -0.21732195132625573, -0.18562031192241921, -0.63767913042640401, -0.66251810488740237, 0.32739091253138108, 0.31719879912773358, 0.57052976335934225, -0.63085557147734861, -0.32090997995451509, 0.11801732139173975, -0.22914176569701664, 0.43878158193465139, 0.00152552343285426, -0.77878744901331443, -0.2154206364017229, -0.44108697476476322, -0.70026220970567188, -0.21015597162801603, -0.81768848556563256, 0.12291968346001558, -0.36764189631202099, -0.053912134959105282, 0.19427618345110181, -0.95604950678208056, -1.0107543007712863, -0.37022193086756733, -0.19570476631315639, -0.18258700694040444, -0.029358161941048021, -0.33587463743557838, -0.63907099954621815, -0.7871741480161194, -0.026860122762995892, -0.20910627529909645, -0.25099439642699012, -0.12990162138336761, 0.31822695461405243, 0.44170377202863292, -1.2668318075013869, -0.19680393231793947, -0.34553338278748241, -0.013221304620122724, 0.30457524826511118, -0.080158919657024166, -0.41415505161829369, -0.66855411044329449, 0.18853276883647158, 0.24304677235687724, 0.22974401712718648, -0.4833088566065169, 0.13080399460827694, 0.17259470259099549, 0.2241708572061612, 0.052256898887154429, -0.045596372233401565, -0.39506238263569499, 0.12569190159090163, -0.4721743047807696, -0.29278957576098419, -0.9752184227786842, -0.25382820554398289, -0.24102069174183499, 0.05869424648815922, 0.054377393485893488, 0.13720777018147434, -0.10863966111290073, -1.1711962847351609, -0.27957674163531454, -0.12115526367493691, -0.066125528733323113, 0.05067779874665769, 0.13724943892750677, 0.31189686278932377, -1.8844581296160039, 0.22928657511611331, 0.10984186635778115, 0.071968296676460514, -0.65540325781478659, 0.044610162234377124, 0.61706372891257, -0.25799846671851207, 0.53227732994701604, 0.063780646982127417, -0.63403958794644599, 0.019079478562575993, 0.10571363452425656, 0.28299368973428785, 0.37285480394059239, 0.8298738351201258, 0.40241708055057163, 0.36141164573787748, 0.19056916248684336, 0.013422788112157441, 0.21362396374133141, 0.21170039337711832, 0.65682922873779259, 0.17996389610488131, 0.17618912940075548, 0.055837051967029337, 0.47635947441407112, 0.14570247218735968, 0.022010922139159592, -0.34301868024192605, 0.042987086108539185, 0.16997479685535816, 0.39676217439483719, -0.50294166186356248, -0.077584879822847522, -0.0026812849694046806, -0.0070304765807457804, 0.00086139318774401566, -0.068417167745508378, -0.44192544985797499, 0.017838715441324191, 0.053932438569921172, -0.37407702152340538, -0.76836462499835445, -0.37659752859953943, 0.070476405022610877, 0.031114715704678546, 1.8227698050980026, 0.031057294312271038, -0.13804023408858021, -0.31585092123314185, -0.19416679802293027, 0.025952485208974214, 1.8092351684606967, -0.10854939135684478, 0.08010299113698828, -0.30365162152054137, -0.45867924043820557, -0.9907813041268736, 0.086295581246083719, 0.1988015460304926, -0.36647646679263252, -0.20680337213014846, 0.32880725417254086, 0.26241701540156215, 0.54863413978261344, 0.34283631736968961, -0.26544297805954836, -0.76802941179112294, 0.48618771275602263, -0.17148941995074718, -0.18424946516473192, -0.46877020507574757, -0.10282523274600154, 0.28116765952051342, -1.1168846512043153, -0.4122194383644624, -0.08946406838361208, 0.18021426909026717, -0.10122540662981004, 0.034213322330504753, -0.19732428915492381, 0.59334289938553164, 0.10978773147054675, 0.16920133114065913, -0.24319825871584588, 0.063278817627801465, -0.0053210473581691339, 0.12036277227622055, 0.4954460516523374, 0.93152959188593254, 0.036615525972745873, 0.02947105801327549, -0.27681852142063801, -0.23873878939551088, -0.21665100111385471, -3.0713035278356062, -0.153670300139091, 0.011716097282919252, 0.23098374549162623, 0.13505030603550353, -0.75502016908447978, 0.044680721099331577, -0.22581480734820017, 0.13152111986063453, 0.16064478356905196, 0.18649061839766412, 0.26551310720639176, 0.53017189293793598, 0.2323226250746121, -0.021655146127859664, -0.22674190098252556, -1.3961601698058137, 0.045511220025551323, -0.023144530320390034, -0.50604729415443894, -0.17165752661416975, 0.11530253323130966, 0.45783195903960688, 0.58026670504182676, -0.28292510778184193, 0.02837341603528528, 0.0078272735048361634, 0.034593272211199379, -0.082238693151600803, -0.34756628453207994, 0.44600355852726253, 0.163803210378553, -0.043893862101987792, 0.026875668835038134, -0.17587390803302924, 0.12928521923450517, 0.082171324305999369, -3.0190262777829666, -0.18349508738568443, -0.24543667116491794, -0.34526437041012031, -0.021758087131575017, 0.064281903098361251, 1.0481104132177597, -0.027442858732998988, 0.25788067594374803, -0.779585720281598, 0.69115914670106138, -0.027912832394080687, 0.22368767638971607, 0.42651215593772057, -0.56438259272042213, -0.26660630249361694, -0.2553356224806303, 0.14030953694797085, -0.38264824382232498, 0.32734665204074642, 0.0012368998190632257, -0.9691860595924684, -0.63185821766632921, 0.67793048107631282, -0.2903510748026934, -0.75919356768443591, 0.37754940658972574, -0.74252243902966908, 0.20790525870507778, -0.41782884858009622, -0.30994657425487454, 0.59574664448934989, -0.36427791414185029, 0.47770637652271097, 0.30565099136409057, -0.2608414654416093, 0.44905299277085126, -0.051991599101275668, -0.76613383923718648, 0.26247674056966031, 0.44122808422816334, -0.12209400598795514, -0.42067659930207513, -0.58737340127198967, -0.17351593581176553, -0.52610314662568092, 0.26139575203507082, -0.81021910944616826, -0.25661050077094449, -1.1400241067264578, -1.320307137283143, -0.24901694375718927, -0.31413051458652524, -0.19495899796908719, 0.35749666435468325, 0.47633841409308547, -0.65329849736537227, 0.70388595046138824, -0.41425035995376541, -0.20411908070193899, 0.11876188534322868, -0.025195379309941549, -0.19898417249985315, -0.7735768879078414, -0.84583681811724831, -0.84220139840200803, 0.19089262532721252, -0.86934661086904286, -0.090277287796316677, -1.0623340655471751, 0.64513368861590659, -0.98781931833136993, 0.3435938169884355, 0.40634749244209473, 0.29829266242097874, -0.71225918026146551, -0.81501484244389255, -0.47411275573432243, -0.28651194973054611, -0.27830466589415653, 0.30192692718285674, -0.56494839564160404, -0.68349639960981567, 0.30431709523408318, 0.039827223020375183, 0.064159596777665223, -0.023542117474316959, -0.095245996848062633, -0.81369164919214287, -1.5258433487073684, -0.9811679865489854, -0.10709897431523935, -0.6181777597589404, -0.54107778565070419, 0.22566883701084225, 0.27272603619088032, 0.79237209885925763, 0.59722532197116052, 0.85278460568989978, 0.34185055473527592, 0.2232401650842098, 0.84456968677403488, 0.19609818874455276, 0.42159128269755158, -0.13434598160500252, 0.42271429857333293, 0.19721734372828323, 0.95716493419833681, -0.11323642144984838, 0.5144536690550463, -0.038569957361822886, -0.11737603159927493, 0.015739791107657553, 0.50006496403261469, -0.25592736218907947, 0.051931765987549186, -0.28564310762687439, -0.019757271559068038, 0.43357926821806153, -0.093304670201876161, -0.31472818434645999, 0.12865529851909333, 1.2016137762589436, 0.23948059779097472, -0.25588742824318089, -0.64984585693320873, -0.21129080984149309, 0.25871989243136523, 1.2077250296119109, -0.88206594891073409, 0.31959989690250284, 0.20049206590115773, -0.35281973959328988, 0.16894356852634465, 0.31328550440161895, -1.0374822713328145, 0.082512695479744477, -0.097738639036174024, 0.0037669271307603936, -0.025940539555389906, 0.42459597487413586, -0.52545961612452607, 0.46141436500937338, -0.2407110535963744, -0.52857258189754242, 0.34974910560376254, -0.61860737991223536, -0.2684154501991593, -0.85453663798219071, 0.24605267663779665, 0.20987297838208852, 0.12865106297107259, 0.34934377922749293, 0.4220716014887404, -0.47381659385244951, -0.66860814013076653, -0.19977570443387169, -0.47125857932987514, -0.044736061146207672, -0.12378263647856219, 0.0035432867534228659, 0.41234338046328456, -0.26302726421113659, 0.19595371998344194, -0.32084368171831429, -1.3143673923904344, 0.86751420142862445, -0.77942309770534735, -0.25531891955800151, -0.53700888871870578, 0.8071441870006042, -1.5405326342631882, -0.23645198977342111, -0.36891920942625439, 0.13518759397542254, -0.12916654025334073, 0.10639035003584091, -0.65517586907437475, -0.24166445665516784, -0.072136468615292826, -0.31709921959705445, -0.018698588433199693, 0.59562870380602817, 0.68615775972530157, 0.052347489468523592, -0.23074797800372485, -0.086439736135067557, 0.067268121576213785, -0.013149409563899069, 0.014432233673689319, -0.46946951790128161, 0.084122168183354232, 0.1539520309455841, -0.017100738366009477, 0.044089707493901516, 0.26468244313830147, -0.017889051788001452, -0.10891131588113208, -0.075594374139504525, -0.12393865947835007, 0.022095314882633419, 0.17390157209292326, -0.12047369907913287, -0.35067751596559499, -1.3669468325869112, -0.24602276352259386, 0.054646140383132161, 0.26073118188833422, 0.10274078804448285, -0.20074409877106772, -0.75373047189600306, -1.4474139633480869, -0.65219325643974446, -0.16301362165010824, 0.042238523777461977, -0.13376406257342119, 0.089842297599819196, 0.42817408599951717, -2.5819306619831623, 0.52415781575721798, 0.19341361061431966, -0.14678057278172538, -0.057102459693204877, -1.0710218099665989, -0.56019077889217561, -0.47072947976289381, -0.027413598214694638, -0.22116294180846455, -0.12367315477313719, 0.12933324745596081, 0.33771308472163802, -0.73665845313107081, -0.15561420037355439, -0.31047932387622151, 0.0089761142699981648, -0.89659549039837882, 0.0066084457962015397, -1.0061281225880647, -0.40284688648992584, 0.042409793953320431, 0.23182678731480272, -0.11759582998327953, -0.22466347493015815, -0.23888003757134205, 0.44995614085446717, 0.16113484423776914, -0.030392439547797225, 0.002280664121179222, -0.046684600209798949, 0.28803804464938393, 0.12932603977515555, -0.5596365353373417, -0.22285831970678657, 0.077576359821673088, -0.11082846718217007, 0.049366440208775737, -0.21887319989794735, -0.38869927385117747, -1.7985504381130348, -0.10705148520488277, -0.0014421543554276944, -0.13067246310662417, -0.028672630701787129, -0.19274105731827584, -1.1607051624609162, 0.012314547896388285, -0.44436361178028749, 0.034320415213815986, -0.72734357120841786, 0.7900318828179147, -0.25427456227674616, -0.49207338469215267, -0.82872354656123937, 0.30447308360877368, 0.668678205936037, -0.1365293728801753, 0.34540642776140257, 0.45779644843974371, 0.40053687028715601, 0.10048124604114105, -0.73595300685433829, -0.97613779520649357, -0.14443569500497874, -0.71044690572412705, 0.38996545112873943, 0.27004601617653601, 0.45223097199651174, -0.96733726241281259, 0.24568458902052331, 0.37302700121362747, 0.02058660931859068, 0.091637309484001658, -0.32493300565506, -0.090014462826387809, -0.25399057772281791, -0.26202234831172649, 0.24004167340703483, -0.24413057638615357, 0.11138867142976393, -0.10447771535348316, -0.27515034225082263, -0.22820482137102804, -0.0094750007299421492, 0.26087968737800726, -1.3291195635025101, -0.72864693715606543, -0.19600885900192114, -0.44694394779806962, -0.91455412226813515]</Parameters>
			</FullConnection>
			<FullConnection class="pybrain.structure.connections.full.FullConnection" name="FullConnection-8">
				<outmod val="LinearLayer-10"/>
				<inmod val="SigmoidLayer-11"/>
				<Parameters>[-0.066263370948722422, 0.059567429000153112, -0.038912960376945395, 0.10395502353943648, 0.21312696355177702, 0.15911851840980218, 0.16046214615703644, -0.14684795593051947, -0.121464390105551, -0.042176350704858576, -0.013178553862052423, -0.54857096485988288, -0.2092405169727003, -0.083992716974765388, 0.18671555026478542, 0.23396185263653332, 0.1641833562461581, -0.25015918227912615, 0.10884977497237638, 0.16626603304975421, 0.12471369424566935, 0.37511907652217735, 0.042809267767336359, -0.13734586336576665, 0.83378110274368, 0.11696923373971753, -0.1387548309717701, -0.29345086831121547, -0.075465175127093276, 0.14560788195301888, -0.34147987467505908, 0.0053451576234814294, 0.24540040283819159, 0.13641899690446987, -0.14229258464569841, -0.017088770498228843, -0.10771113993993205, -0.0085085329503154609, -0.32383638590127412, -0.42824822525462647, 0.27394894061965019, 0.33496060330436689, 0.34833378183632879, 0.12038642360343883, -0.24029522156972197, 0.42240645114023156, 0.091009619495405605, -0.18880341928171435, 0.3406636520273138, -0.071546478345017164]</Parameters>
			</FullConnection>
		</Connections>
	</Network>
</PyBrain>
